.version 52 0 
.class super test 
.super java/lang/Object 

.method <init> : ()V 
    .code stack 1 locals 1 
L0:     aload_0 
L1:     invokespecial Method java/lang/Object <init> ()V 
L4:     return 
L5:     
        .linenumbertable 
            L0 5 
        .end linenumbertable 
        .localvariabletable 
            0 is this Ltest; from L0 to L5 
        .end localvariabletable 
    .end code 
.end method 

.method public static main : ([Ljava/lang/String;)V 
    .code stack 7 locals 80 
L0:     ldc '8da4ef21b864d2cc526dbdb2a120bd2874c36c9d0a1fb7f8c63d7f7a8b41de8f' 
L2:     astore_1 
L3:     aload_1 
L4:     astore_2 
L5:     new java/math/BigInteger 
L8:     dup 
L9:     aload_2 
L10:    bipush 16 
L12:    invokespecial Method java/math/BigInteger <init> (Ljava/lang/String;I)V 
L15:    astore_3 
L16:    aload_3 
L17:    invokevirtual Method java/math/BigInteger bitLength ()I 
L20:    new ECDomainParameters 
L23:    dup 
L24:    invokestatic Method CustomNamedCurves getByName ()LX9ECParameters; 
L27:    invokestatic Method java/util/Objects requireNonNull (Ljava/lang/Object;)Ljava/lang/Object; 
L30:    checkcast X9ECParameters 
L33:    invokevirtual Method X9ECParameters getCurve ()LECCurve; 
L36:    invokestatic Method CustomNamedCurves getByName ()LX9ECParameters; 
L39:    invokevirtual Method X9ECParameters getG ()LECPoint; 
L42:    invokestatic Method CustomNamedCurves getByName ()LX9ECParameters; 
L45:    invokevirtual Method X9ECParameters getN ()Ljava/math/BigInteger; 
L48:    invokestatic Method CustomNamedCurves getByName ()LX9ECParameters; 
L51:    invokevirtual Method X9ECParameters getH ()Ljava/math/BigInteger; 
L54:    invokespecial Method ECDomainParameters <init> (LECCurve;LECPoint;Ljava/math/BigInteger;Ljava/math/BigInteger;)V 
L57:    invokevirtual Method ECDomainParameters getN ()Ljava/math/BigInteger; 
L60:    invokevirtual Method java/math/BigInteger bitLength ()I 
L63:    if_icmple L105 
L66:    aload_3 
L67:    new ECDomainParameters 
L70:    dup 
L71:    invokestatic Method CustomNamedCurves getByName ()LX9ECParameters; 
L74:    invokevirtual Method X9ECParameters getCurve ()LECCurve; 
L77:    invokestatic Method CustomNamedCurves getByName ()LX9ECParameters; 
L80:    invokevirtual Method X9ECParameters getG ()LECPoint; 
L83:    invokestatic Method CustomNamedCurves getByName ()LX9ECParameters; 
L86:    invokevirtual Method X9ECParameters getN ()Ljava/math/BigInteger; 
L89:    invokestatic Method CustomNamedCurves getByName ()LX9ECParameters; 
L92:    invokevirtual Method X9ECParameters getH ()Ljava/math/BigInteger; 
L95:    invokespecial Method ECDomainParameters <init> (LECCurve;LECPoint;Ljava/math/BigInteger;Ljava/math/BigInteger;)V 
L98:    invokevirtual Method ECDomainParameters getN ()Ljava/math/BigInteger; 
L101:   invokevirtual Method java/math/BigInteger mod (Ljava/math/BigInteger;)Ljava/math/BigInteger; 
L104:   astore_3 

        .stack append Object java/lang/String Object java/lang/String Object java/math/BigInteger 
L105:   new FixedPointCombMultiplier 
L108:   dup 
L109:   invokespecial Method FixedPointCombMultiplier <init> ()V 
L112:   new ECDomainParameters 
L115:   dup 
L116:   invokestatic Method CustomNamedCurves getByName ()LX9ECParameters; 
L119:   invokevirtual Method X9ECParameters getCurve ()LECCurve; 
L122:   invokestatic Method CustomNamedCurves getByName ()LX9ECParameters; 
L125:   invokevirtual Method X9ECParameters getG ()LECPoint; 
L128:   invokestatic Method CustomNamedCurves getByName ()LX9ECParameters; 
L131:   invokevirtual Method X9ECParameters getN ()Ljava/math/BigInteger; 
L134:   invokestatic Method CustomNamedCurves getByName ()LX9ECParameters; 
L137:   invokevirtual Method X9ECParameters getH ()Ljava/math/BigInteger; 
L140:   invokespecial Method ECDomainParameters <init> (LECCurve;LECPoint;Ljava/math/BigInteger;Ljava/math/BigInteger;)V 
L143:   invokevirtual Method ECDomainParameters getG ()LECPoint; 
L146:   aload_3 
L147:   invokevirtual Method FixedPointCombMultiplier multiply (LECPoint;Ljava/math/BigInteger;)LECPoint; 
L150:   astore 4 
L152:   aload 4 
L154:   iconst_0 
L155:   invokevirtual Method ECPoint getEncoded (Z)[B 
L158:   astore 5 
L160:   aload 5 
L162:   arraylength 
L163:   iconst_1 
L164:   isub 
L165:   istore 6 
L167:   iload 6 
L169:   ifge L201 
L172:   new java/lang/IllegalArgumentException 
L175:   dup 
L176:   new java/lang/StringBuilder 
L179:   dup 
L180:   invokespecial Method java/lang/StringBuilder <init> ()V 
L183:   ldc '1 > ' 
L185:   invokevirtual Method java/lang/StringBuilder append (Ljava/lang/String;)Ljava/lang/StringBuilder; 
L188:   aload 5 
L190:   arraylength 
L191:   invokevirtual Method java/lang/StringBuilder append (I)Ljava/lang/StringBuilder; 
L194:   invokevirtual Method java/lang/StringBuilder toString ()Ljava/lang/String; 
L197:   invokespecial Method java/lang/IllegalArgumentException <init> (Ljava/lang/String;)V 
L200:   athrow 

        .stack append Object ECPoint Object [B Integer 
L201:   iload 6 
L203:   newarray byte 
L205:   astore 7 
L207:   aload 5 
L209:   iconst_1 
L210:   aload 7 
L212:   iconst_0 
L213:   aload 5 
L215:   arraylength 
L216:   iconst_1 
L217:   isub 
L218:   iload 6 
L220:   invokestatic Method java/lang/Math min (II)I 
L223:   invokestatic Method java/lang/System arraycopy (Ljava/lang/Object;ILjava/lang/Object;II)V 
L226:   new java/math/BigInteger 
L229:   dup 
L230:   iconst_1 
L231:   aload 7 
L233:   invokespecial Method java/math/BigInteger <init> (I[B)V 
L236:   astore 8 
L238:   aload 8 
L240:   bipush 16 
L242:   invokevirtual Method java/math/BigInteger toString (I)Ljava/lang/String; 
L245:   astore 11 
L247:   aload 11 
L249:   invokevirtual Method java/lang/String length ()I 
L252:   istore 12 
L254:   iload 12 
L256:   sipush 128 
L259:   if_icmple L301 
L262:   new java/lang/UnsupportedOperationException 
L265:   dup 
L266:   new java/lang/StringBuilder 
L269:   dup 
L270:   invokespecial Method java/lang/StringBuilder <init> ()V 
L273:   ldc 'Value ' 
L275:   invokevirtual Method java/lang/StringBuilder append (Ljava/lang/String;)Ljava/lang/StringBuilder; 
L278:   aload 11 
L280:   invokevirtual Method java/lang/StringBuilder append (Ljava/lang/String;)Ljava/lang/StringBuilder; 
L283:   ldc 'is larger then length ' 
L285:   invokevirtual Method java/lang/StringBuilder append (Ljava/lang/String;)Ljava/lang/StringBuilder; 
L288:   sipush 128 
L291:   invokevirtual Method java/lang/StringBuilder append (I)Ljava/lang/StringBuilder; 
L294:   invokevirtual Method java/lang/StringBuilder toString ()Ljava/lang/String; 
L297:   invokespecial Method java/lang/UnsupportedOperationException <init> (Ljava/lang/String;)V 
L300:   athrow 

        .stack full 
            locals Object [Ljava/lang/String; Object java/lang/String Object java/lang/String Object java/math/BigInteger Object ECPoint Object [B Integer Object [B Object java/math/BigInteger Top Top Object java/lang/String Integer 
            stack 
        .end stack 
L301:   aload 8 
L303:   invokevirtual Method java/math/BigInteger signum ()I 
L306:   ifge L319 
L309:   new java/lang/UnsupportedOperationException 
L312:   dup 
L313:   ldc 'Value cannot be negative' 
L315:   invokespecial Method java/lang/UnsupportedOperationException <init> (Ljava/lang/String;)V 
L318:   athrow 

        .stack same 
L319:   iload 12 
L321:   sipush 128 
L324:   if_icmpge L372 
L327:   new java/lang/StringBuilder 
L330:   dup 
L331:   invokespecial Method java/lang/StringBuilder <init> ()V 
L334:   new java/lang/String 
L337:   dup 
L338:   sipush 128 
L341:   iload 12 
L343:   isub 
L344:   newarray char 
L346:   invokespecial Method java/lang/String <init> ([C)V 
L349:   ldc '\x00' 
L351:   bipush 48 
L353:   invokestatic Method java/lang/String valueOf (C)Ljava/lang/String; 
L356:   invokevirtual Method java/lang/String replace (Ljava/lang/CharSequence;Ljava/lang/CharSequence;)Ljava/lang/String; 
L359:   invokevirtual Method java/lang/StringBuilder append (Ljava/lang/String;)Ljava/lang/StringBuilder; 
L362:   aload 11 
L364:   invokevirtual Method java/lang/StringBuilder append (Ljava/lang/String;)Ljava/lang/StringBuilder; 
L367:   invokevirtual Method java/lang/StringBuilder toString ()Ljava/lang/String; 
L370:   astore 11 

        .stack same 
L372:   new java/lang/StringBuilder 
L375:   dup 
L376:   invokespecial Method java/lang/StringBuilder <init> ()V 
L379:   ldc '0x' 
L381:   invokevirtual Method java/lang/StringBuilder append (Ljava/lang/String;)Ljava/lang/StringBuilder; 
L384:   aload 11 
L386:   invokevirtual Method java/lang/StringBuilder append (Ljava/lang/String;)Ljava/lang/StringBuilder; 
L389:   invokevirtual Method java/lang/StringBuilder toString ()Ljava/lang/String; 
L392:   astore 10 
L394:   aload 10 
L396:   invokevirtual Method java/lang/String length ()I 
L399:   ifeq L444 
L402:   aload 10 
L404:   invokevirtual Method java/lang/String length ()I 
L407:   iconst_1 
L408:   if_icmple L444 
L411:   aload 10 
L413:   iconst_0 
L414:   invokevirtual Method java/lang/String charAt (I)C 
L417:   bipush 48 
L419:   if_icmpne L444 
L422:   aload 10 
L424:   iconst_1 
L425:   invokevirtual Method java/lang/String charAt (I)C 
L428:   bipush 120 
L430:   if_icmpne L444 
L433:   aload 10 
L435:   iconst_2 
L436:   invokevirtual Method java/lang/String substring (I)Ljava/lang/String; 
L439:   astore 9 
L441:   goto L448 

        .stack full 
            locals Object [Ljava/lang/String; Object java/lang/String Object java/lang/String Object java/math/BigInteger Object ECPoint Object [B Integer Object [B Object java/math/BigInteger Top Object java/lang/String Object java/lang/String Integer 
            stack 
        .end stack 
L444:   aload 10 
L446:   astore 9 

        .stack full 
            locals Object [Ljava/lang/String; Object java/lang/String Object java/lang/String Object java/math/BigInteger Object ECPoint Object [B Integer Object [B Object java/math/BigInteger Object java/lang/String Object java/lang/String Object java/lang/String Integer 
            stack 
        .end stack 
L448:   aload 9 
L450:   invokevirtual Method java/lang/String length ()I 
L453:   sipush 128 
L456:   if_icmpge L507 
L459:   new java/lang/StringBuilder 
L462:   dup 
L463:   invokespecial Method java/lang/StringBuilder <init> ()V 
L466:   new java/lang/String 
L469:   dup 
L470:   sipush 128 
L473:   aload 9 
L475:   invokevirtual Method java/lang/String length ()I 
L478:   isub 
L479:   newarray char 
L481:   invokespecial Method java/lang/String <init> ([C)V 
L484:   ldc '\x00' 
L486:   bipush 48 
L488:   invokestatic Method java/lang/String valueOf (C)Ljava/lang/String; 
L491:   invokevirtual Method java/lang/String replace (Ljava/lang/CharSequence;Ljava/lang/CharSequence;)Ljava/lang/String; 
L494:   invokevirtual Method java/lang/StringBuilder append (Ljava/lang/String;)Ljava/lang/StringBuilder; 
L497:   aload 9 
L499:   invokevirtual Method java/lang/StringBuilder append (Ljava/lang/String;)Ljava/lang/StringBuilder; 
L502:   invokevirtual Method java/lang/StringBuilder toString ()Ljava/lang/String; 
L505:   astore 9 

        .stack same 
L507:   aload 9 
L509:   invokevirtual Method java/lang/String length ()I 
L512:   ifeq L550 
L515:   aload 9 
L517:   invokevirtual Method java/lang/String length ()I 
L520:   iconst_1 
L521:   if_icmple L550 
L524:   aload 9 
L526:   iconst_0 
L527:   invokevirtual Method java/lang/String charAt (I)C 
L530:   bipush 48 
L532:   if_icmpne L550 
L535:   aload 9 
L537:   iconst_1 
L538:   invokevirtual Method java/lang/String charAt (I)C 
L541:   bipush 120 
L543:   if_icmpne L550 
L546:   iconst_1 
L547:   goto L551 

        .stack same 
L550:   iconst_0 

        .stack stack_1 Integer 
L551:   istore 16 
L553:   iload 16 
L555:   ifeq L569 
L558:   aload 9 
L560:   iconst_2 
L561:   invokevirtual Method java/lang/String substring (I)Ljava/lang/String; 
L564:   astore 15 
L566:   goto L573 

        .stack full 
            locals Object [Ljava/lang/String; Object java/lang/String Object java/lang/String Object java/math/BigInteger Object ECPoint Object [B Integer Object [B Object java/math/BigInteger Object java/lang/String Object java/lang/String Object java/lang/String Integer Top Top Top Integer 
            stack 
        .end stack 
L569:   aload 9 
L571:   astore 15 

        .stack full 
            locals Object [Ljava/lang/String; Object java/lang/String Object java/lang/String Object java/math/BigInteger Object ECPoint Object [B Integer Object [B Object java/math/BigInteger Object java/lang/String Object java/lang/String Object java/lang/String Integer Top Top Object java/lang/String Integer 
            stack 
        .end stack 
L573:   aload 15 
L575:   invokevirtual Method java/lang/String length ()I 
L578:   istore 17 
L580:   iload 17 
L582:   ifne L593 
L585:   iconst_0 
L586:   newarray byte 
L588:   astore 14 
L590:   goto L703 

        .stack append Integer 
L593:   iload 17 
L595:   iconst_2 
L596:   irem 
L597:   ifeq L632 
L600:   iload 17 
L602:   iconst_2 
L603:   idiv 
L604:   iconst_1 
L605:   iadd 
L606:   newarray byte 
L608:   astore 18 
L610:   aload 18 
L612:   iconst_0 
L613:   aload 15 
L615:   iconst_0 
L616:   invokevirtual Method java/lang/String charAt (I)C 
L619:   bipush 16 
L621:   invokestatic Method java/lang/Character digit (CI)I 
L624:   i2b 
L625:   bastore 
L626:   iconst_1 
L627:   istore 19 
L629:   goto L643 

        .stack same 
L632:   iload 17 
L634:   iconst_2 
L635:   idiv 
L636:   newarray byte 
L638:   astore 18 
L640:   iconst_0 
L641:   istore 19 

        .stack append Object [B Integer 
L643:   iload 19 
L645:   istore 20 

        .stack append Integer 
L647:   iload 20 
L649:   iload 17 
L651:   if_icmpge L699 
L654:   aload 18 
L656:   iload 20 
L658:   iconst_1 
L659:   iadd 
L660:   iconst_2 
L661:   idiv 
L662:   aload 15 
L664:   iload 20 
L666:   invokevirtual Method java/lang/String charAt (I)C 
L669:   bipush 16 
L671:   invokestatic Method java/lang/Character digit (CI)I 
L674:   iconst_4 
L675:   ishl 
L676:   aload 15 
L678:   iload 20 
L680:   iconst_1 
L681:   iadd 
L682:   invokevirtual Method java/lang/String charAt (I)C 
L685:   bipush 16 
L687:   invokestatic Method java/lang/Character digit (CI)I 
L690:   iadd 
L691:   i2b 
L692:   bastore 
L693:   iinc 20 2 
L696:   goto L647 

        .stack chop 1 
L699:   aload 18 
L701:   astore 14 

        .stack full 
            locals Object [Ljava/lang/String; Object java/lang/String Object java/lang/String Object java/math/BigInteger Object ECPoint Object [B Integer Object [B Object java/math/BigInteger Object java/lang/String Object java/lang/String Object java/lang/String Integer Top Object [B Object java/lang/String Integer Integer 
            stack 
        .end stack 
L703:   new Keccak$Digest256 
L706:   dup 
L707:   invokespecial Method Keccak$Digest256 <init> ()V 
L710:   astore 18 
L712:   aload 18 
L714:   aload 14 
L716:   iconst_0 
L717:   aload 14 
L719:   arraylength 
L720:   invokevirtual Method Keccak$DigestKeccak update ([BII)V 
L723:   aload 18 
L725:   invokevirtual Method Keccak$DigestKeccak digest ()[B 
L728:   astore 19 
L730:   iload 16 
L732:   ifeq L746 
L735:   aload 9 
L737:   iconst_2 
L738:   invokevirtual Method java/lang/String substring (I)Ljava/lang/String; 
L741:   astore 21 
L743:   goto L750 

        .stack append Object Keccak$DigestKeccak Object [B 
L746:   aload 9 
L748:   astore 21 

        .stack append Top Object java/lang/String 
L750:   aload 21 
L752:   invokevirtual Method java/lang/String length ()I 
L755:   istore 22 
L757:   iload 22 
L759:   ifne L770 
L762:   iconst_0 
L763:   newarray byte 
L765:   astore 20 
L767:   goto L880 

        .stack append Integer 
L770:   iload 22 
L772:   iconst_2 
L773:   irem 
L774:   ifeq L809 
L777:   iload 22 
L779:   iconst_2 
L780:   idiv 
L781:   iconst_1 
L782:   iadd 
L783:   newarray byte 
L785:   astore 23 
L787:   aload 23 
L789:   iconst_0 
L790:   aload 21 
L792:   iconst_0 
L793:   invokevirtual Method java/lang/String charAt (I)C 
L796:   bipush 16 
L798:   invokestatic Method java/lang/Character digit (CI)I 
L801:   i2b 
L802:   bastore 
L803:   iconst_1 
L804:   istore 24 
L806:   goto L820 

        .stack same 
L809:   iload 22 
L811:   iconst_2 
L812:   idiv 
L813:   newarray byte 
L815:   astore 23 
L817:   iconst_0 
L818:   istore 24 

        .stack append Object [B Integer 
L820:   iload 24 
L822:   istore 25 

        .stack append Integer 
L824:   iload 25 
L826:   iload 22 
L828:   if_icmpge L876 
L831:   aload 23 
L833:   iload 25 
L835:   iconst_1 
L836:   iadd 
L837:   iconst_2 
L838:   idiv 
L839:   aload 21 
L841:   iload 25 
L843:   invokevirtual Method java/lang/String charAt (I)C 
L846:   bipush 16 
L848:   invokestatic Method java/lang/Character digit (CI)I 
L851:   iconst_4 
L852:   ishl 
L853:   aload 21 
L855:   iload 25 
L857:   iconst_1 
L858:   iadd 
L859:   invokevirtual Method java/lang/String charAt (I)C 
L862:   bipush 16 
L864:   invokestatic Method java/lang/Character digit (CI)I 
L867:   iadd 
L868:   i2b 
L869:   bastore 
L870:   iinc 25 2 
L873:   goto L824 

        .stack chop 1 
L876:   aload 23 
L878:   astore 20 

        .stack full 
            locals Object [Ljava/lang/String; Object java/lang/String Object java/lang/String Object java/math/BigInteger Object ECPoint Object [B Integer Object [B Object java/math/BigInteger Object java/lang/String Object java/lang/String Object java/lang/String Integer Top Object [B Object java/lang/String Integer Integer Object Keccak$DigestKeccak Object [B Object [B Object java/lang/String Integer 
            stack 
        .end stack 
L880:   new Keccak$Digest256 
L883:   dup 
L884:   invokespecial Method Keccak$Digest256 <init> ()V 
L887:   astore 23 
L889:   aload 23 
L891:   aload 20 
L893:   iconst_0 
L894:   aload 20 
L896:   arraylength 
L897:   invokevirtual Method Keccak$DigestKeccak update ([BII)V 
L900:   aload 23 
L902:   invokevirtual Method Keccak$DigestKeccak digest ()[B 
L905:   astore 24 
L907:   new java/lang/StringBuilder 
L910:   dup 
L911:   invokespecial Method java/lang/StringBuilder <init> ()V 
L914:   astore 25 
L916:   aload 25 
L918:   ldc '0x' 
L920:   invokevirtual Method java/lang/StringBuilder append (Ljava/lang/String;)Ljava/lang/StringBuilder; 
L923:   pop 
L924:   aload 19 
L926:   astore 26 
L928:   aload 26 
L930:   arraylength 
L931:   istore 27 
L933:   iconst_0 
L934:   istore 28 

        .stack full 
            locals Object [Ljava/lang/String; Object java/lang/String Object java/lang/String Object java/math/BigInteger Object ECPoint Object [B Integer Object [B Object java/math/BigInteger Object java/lang/String Object java/lang/String Object java/lang/String Integer Top Object [B Object java/lang/String Integer Integer Object Keccak$DigestKeccak Object [B Object [B Object java/lang/String Integer Object Keccak$DigestKeccak Object [B Object java/lang/StringBuilder Object [B Integer Integer 
            stack 
        .end stack 
L936:   iload 28 
L938:   iload 27 
L940:   if_icmpge L983 
L943:   aload 26 
L945:   iload 28 
L947:   baload 
L948:   istore 29 
L950:   aload 25 
L952:   ldc '%02x' 
L954:   iconst_1 
L955:   anewarray java/lang/Object 
L958:   dup 
L959:   iconst_0 
L960:   iload 29 
L962:   sipush 255 
L965:   iand 
L966:   invokestatic Method java/lang/Integer valueOf (I)Ljava/lang/Integer; 
L969:   aastore 
L970:   invokestatic Method java/lang/String format (Ljava/lang/String;[Ljava/lang/Object;)Ljava/lang/String; 
L973:   invokevirtual Method java/lang/StringBuilder append (Ljava/lang/String;)Ljava/lang/StringBuilder; 
L976:   pop 
L977:   iinc 28 1 
L980:   goto L936 

        .stack chop 3 
L983:   new java/lang/StringBuilder 
L986:   dup 
L987:   invokespecial Method java/lang/StringBuilder <init> ()V 
L990:   astore 26 
L992:   aload 26 
L994:   ldc '0x' 
L996:   invokevirtual Method java/lang/StringBuilder append (Ljava/lang/String;)Ljava/lang/StringBuilder; 
L999:   pop 
L1000:  aload 24 
L1002:  astore 27 
L1004:  aload 27 
L1006:  arraylength 
L1007:  istore 28 
L1009:  iconst_0 
L1010:  istore 29 

        .stack full 
            locals Object [Ljava/lang/String; Object java/lang/String Object java/lang/String Object java/math/BigInteger Object ECPoint Object [B Integer Object [B Object java/math/BigInteger Object java/lang/String Object java/lang/String Object java/lang/String Integer Top Object [B Object java/lang/String Integer Integer Object Keccak$DigestKeccak Object [B Object [B Object java/lang/String Integer Object Keccak$DigestKeccak Object [B Object java/lang/StringBuilder Object java/lang/StringBuilder Object [B Integer Integer 
            stack 
        .end stack 
L1012:  iload 29 
L1014:  iload 28 
L1016:  if_icmpge L1059 
L1019:  aload 27 
L1021:  iload 29 
L1023:  baload 
L1024:  istore 30 
L1026:  aload 26 
L1028:  ldc '%02x' 
L1030:  iconst_1 
L1031:  anewarray java/lang/Object 
L1034:  dup 
L1035:  iconst_0 
L1036:  iload 30 
L1038:  sipush 255 
L1041:  iand 
L1042:  invokestatic Method java/lang/Integer valueOf (I)Ljava/lang/Integer; 
L1045:  aastore 
L1046:  invokestatic Method java/lang/String format (Ljava/lang/String;[Ljava/lang/Object;)Ljava/lang/String; 
L1049:  invokevirtual Method java/lang/StringBuilder append (Ljava/lang/String;)Ljava/lang/StringBuilder; 
L1052:  pop 
L1053:  iinc 29 1 
L1056:  goto L1012 

        .stack chop 3 
L1059:  aload 26 
L1061:  invokevirtual Method java/lang/StringBuilder toString ()Ljava/lang/String; 
L1064:  aload 25 
L1066:  invokevirtual Method java/lang/StringBuilder toString ()Ljava/lang/String; 
L1069:  invokevirtual Method java/lang/String length ()I 
L1072:  bipush 40 
L1074:  isub 
L1075:  invokevirtual Method java/lang/String substring (I)Ljava/lang/String; 
L1078:  astore 27 
L1080:  iload 16 
L1082:  ifeq L1096 
L1085:  aload 9 
L1087:  iconst_2 
L1088:  invokevirtual Method java/lang/String substring (I)Ljava/lang/String; 
L1091:  astore 29 
L1093:  goto L1100 

        .stack append Object java/lang/String 
L1096:  aload 9 
L1098:  astore 29 

        .stack append Top Object java/lang/String 
L1100:  aload 29 
L1102:  invokevirtual Method java/lang/String length ()I 
L1105:  istore 30 
L1107:  iload 30 
L1109:  ifne L1120 
L1112:  iconst_0 
L1113:  newarray byte 
L1115:  astore 28 
L1117:  goto L1230 

        .stack append Integer 
L1120:  iload 30 
L1122:  iconst_2 
L1123:  irem 
L1124:  ifeq L1159 
L1127:  iload 30 
L1129:  iconst_2 
L1130:  idiv 
L1131:  iconst_1 
L1132:  iadd 
L1133:  newarray byte 
L1135:  astore 31 
L1137:  aload 31 
L1139:  iconst_0 
L1140:  aload 29 
L1142:  iconst_0 
L1143:  invokevirtual Method java/lang/String charAt (I)C 
L1146:  bipush 16 
L1148:  invokestatic Method java/lang/Character digit (CI)I 
L1151:  i2b 
L1152:  bastore 
L1153:  iconst_1 
L1154:  istore 32 
L1156:  goto L1170 

        .stack same 
L1159:  iload 30 
L1161:  iconst_2 
L1162:  idiv 
L1163:  newarray byte 
L1165:  astore 31 
L1167:  iconst_0 
L1168:  istore 32 

        .stack append Object [B Integer 
L1170:  iload 32 
L1172:  istore 33 

        .stack append Integer 
L1174:  iload 33 
L1176:  iload 30 
L1178:  if_icmpge L1226 
L1181:  aload 31 
L1183:  iload 33 
L1185:  iconst_1 
L1186:  iadd 
L1187:  iconst_2 
L1188:  idiv 
L1189:  aload 29 
L1191:  iload 33 
L1193:  invokevirtual Method java/lang/String charAt (I)C 
L1196:  bipush 16 
L1198:  invokestatic Method java/lang/Character digit (CI)I 
L1201:  iconst_4 
L1202:  ishl 
L1203:  aload 29 
L1205:  iload 33 
L1207:  iconst_1 
L1208:  iadd 
L1209:  invokevirtual Method java/lang/String charAt (I)C 
L1212:  bipush 16 
L1214:  invokestatic Method java/lang/Character digit (CI)I 
L1217:  iadd 
L1218:  i2b 
L1219:  bastore 
L1220:  iinc 33 2 
L1223:  goto L1174 

        .stack chop 1 
L1226:  aload 31 
L1228:  astore 28 

        .stack full 
            locals Object [Ljava/lang/String; Object java/lang/String Object java/lang/String Object java/math/BigInteger Object ECPoint Object [B Integer Object [B Object java/math/BigInteger Object java/lang/String Object java/lang/String Object java/lang/String Integer Top Object [B Object java/lang/String Integer Integer Object Keccak$DigestKeccak Object [B Object [B Object java/lang/String Integer Object Keccak$DigestKeccak Object [B Object java/lang/StringBuilder Object java/lang/StringBuilder Object java/lang/String Object [B Object java/lang/String Integer 
            stack 
        .end stack 
L1230:  new Keccak$Digest256 
L1233:  dup 
L1234:  invokespecial Method Keccak$Digest256 <init> ()V 
L1237:  astore 31 
L1239:  aload 31 
L1241:  aload 28 
L1243:  iconst_0 
L1244:  aload 28 
L1246:  arraylength 
L1247:  invokevirtual Method Keccak$DigestKeccak update ([BII)V 
L1250:  aload 31 
L1252:  invokevirtual Method Keccak$DigestKeccak digest ()[B 
L1255:  astore 32 
L1257:  iload 16 
L1259:  ifeq L1273 
L1262:  aload 9 
L1264:  iconst_2 
L1265:  invokevirtual Method java/lang/String substring (I)Ljava/lang/String; 
L1268:  astore 34 
L1270:  goto L1277 

        .stack append Object Keccak$DigestKeccak Object [B 
L1273:  aload 9 
L1275:  astore 34 

        .stack append Top Object java/lang/String 
L1277:  aload 34 
L1279:  invokevirtual Method java/lang/String length ()I 
L1282:  istore 35 
L1284:  iload 35 
L1286:  ifne L1297 
L1289:  iconst_0 
L1290:  newarray byte 
L1292:  astore 33 
L1294:  goto L1407 

        .stack append Integer 
L1297:  iload 35 
L1299:  iconst_2 
L1300:  irem 
L1301:  ifeq L1336 
L1304:  iload 35 
L1306:  iconst_2 
L1307:  idiv 
L1308:  iconst_1 
L1309:  iadd 
L1310:  newarray byte 
L1312:  astore 36 
L1314:  aload 36 
L1316:  iconst_0 
L1317:  aload 34 
L1319:  iconst_0 
L1320:  invokevirtual Method java/lang/String charAt (I)C 
L1323:  bipush 16 
L1325:  invokestatic Method java/lang/Character digit (CI)I 
L1328:  i2b 
L1329:  bastore 
L1330:  iconst_1 
L1331:  istore 37 
L1333:  goto L1347 

        .stack same 
L1336:  iload 35 
L1338:  iconst_2 
L1339:  idiv 
L1340:  newarray byte 
L1342:  astore 36 
L1344:  iconst_0 
L1345:  istore 37 

        .stack append Object [B Integer 
L1347:  iload 37 
L1349:  istore 38 

        .stack append Integer 
L1351:  iload 38 
L1353:  iload 35 
L1355:  if_icmpge L1403 
L1358:  aload 36 
L1360:  iload 38 
L1362:  iconst_1 
L1363:  iadd 
L1364:  iconst_2 
L1365:  idiv 
L1366:  aload 34 
L1368:  iload 38 
L1370:  invokevirtual Method java/lang/String charAt (I)C 
L1373:  bipush 16 
L1375:  invokestatic Method java/lang/Character digit (CI)I 
L1378:  iconst_4 
L1379:  ishl 
L1380:  aload 34 
L1382:  iload 38 
L1384:  iconst_1 
L1385:  iadd 
L1386:  invokevirtual Method java/lang/String charAt (I)C 
L1389:  bipush 16 
L1391:  invokestatic Method java/lang/Character digit (CI)I 
L1394:  iadd 
L1395:  i2b 
L1396:  bastore 
L1397:  iinc 38 2 
L1400:  goto L1351 

        .stack chop 1 
L1403:  aload 36 
L1405:  astore 33 

        .stack full 
            locals Object [Ljava/lang/String; Object java/lang/String Object java/lang/String Object java/math/BigInteger Object ECPoint Object [B Integer Object [B Object java/math/BigInteger Object java/lang/String Object java/lang/String Object java/lang/String Integer Top Object [B Object java/lang/String Integer Integer Object Keccak$DigestKeccak Object [B Object [B Object java/lang/String Integer Object Keccak$DigestKeccak Object [B Object java/lang/StringBuilder Object java/lang/StringBuilder Object java/lang/String Object [B Object java/lang/String Integer Object Keccak$DigestKeccak Object [B Object [B Object java/lang/String Integer 
            stack 
        .end stack 
L1407:  new Keccak$Digest256 
L1410:  dup 
L1411:  invokespecial Method Keccak$Digest256 <init> ()V 
L1414:  astore 36 
L1416:  aload 36 
L1418:  aload 33 
L1420:  iconst_0 
L1421:  aload 33 
L1423:  arraylength 
L1424:  invokevirtual Method Keccak$DigestKeccak update ([BII)V 
L1427:  aload 36 
L1429:  invokevirtual Method Keccak$DigestKeccak digest ()[B 
L1432:  astore 37 
L1434:  iload 16 
L1436:  ifeq L1450 
L1439:  aload 9 
L1441:  iconst_2 
L1442:  invokevirtual Method java/lang/String substring (I)Ljava/lang/String; 
L1445:  astore 39 
L1447:  goto L1454 

        .stack append Object Keccak$DigestKeccak Object [B 
L1450:  aload 9 
L1452:  astore 39 

        .stack append Top Object java/lang/String 
L1454:  aload 39 
L1456:  invokevirtual Method java/lang/String length ()I 
L1459:  istore 40 
L1461:  iload 40 
L1463:  ifne L1474 
L1466:  iconst_0 
L1467:  newarray byte 
L1469:  astore 38 
L1471:  goto L1584 

        .stack append Integer 
L1474:  iload 40 
L1476:  iconst_2 
L1477:  irem 
L1478:  ifeq L1513 
L1481:  iload 40 
L1483:  iconst_2 
L1484:  idiv 
L1485:  iconst_1 
L1486:  iadd 
L1487:  newarray byte 
L1489:  astore 41 
L1491:  aload 41 
L1493:  iconst_0 
L1494:  aload 39 
L1496:  iconst_0 
L1497:  invokevirtual Method java/lang/String charAt (I)C 
L1500:  bipush 16 
L1502:  invokestatic Method java/lang/Character digit (CI)I 
L1505:  i2b 
L1506:  bastore 
L1507:  iconst_1 
L1508:  istore 42 
L1510:  goto L1524 

        .stack same 
L1513:  iload 40 
L1515:  iconst_2 
L1516:  idiv 
L1517:  newarray byte 
L1519:  astore 41 
L1521:  iconst_0 
L1522:  istore 42 

        .stack append Object [B Integer 
L1524:  iload 42 
L1526:  istore 43 

        .stack append Integer 
L1528:  iload 43 
L1530:  iload 40 
L1532:  if_icmpge L1580 
L1535:  aload 41 
L1537:  iload 43 
L1539:  iconst_1 
L1540:  iadd 
L1541:  iconst_2 
L1542:  idiv 
L1543:  aload 39 
L1545:  iload 43 
L1547:  invokevirtual Method java/lang/String charAt (I)C 
L1550:  bipush 16 
L1552:  invokestatic Method java/lang/Character digit (CI)I 
L1555:  iconst_4 
L1556:  ishl 
L1557:  aload 39 
L1559:  iload 43 
L1561:  iconst_1 
L1562:  iadd 
L1563:  invokevirtual Method java/lang/String charAt (I)C 
L1566:  bipush 16 
L1568:  invokestatic Method java/lang/Character digit (CI)I 
L1571:  iadd 
L1572:  i2b 
L1573:  bastore 
L1574:  iinc 43 2 
L1577:  goto L1528 

        .stack chop 1 
L1580:  aload 41 
L1582:  astore 38 

        .stack full 
            locals Object [Ljava/lang/String; Object java/lang/String Object java/lang/String Object java/math/BigInteger Object ECPoint Object [B Integer Object [B Object java/math/BigInteger Object java/lang/String Object java/lang/String Object java/lang/String Integer Top Object [B Object java/lang/String Integer Integer Object Keccak$DigestKeccak Object [B Object [B Object java/lang/String Integer Object Keccak$DigestKeccak Object [B Object java/lang/StringBuilder Object java/lang/StringBuilder Object java/lang/String Object [B Object java/lang/String Integer Object Keccak$DigestKeccak Object [B Object [B Object java/lang/String Integer Object Keccak$DigestKeccak Object [B Object [B Object java/lang/String Integer 
            stack 
        .end stack 
L1584:  new Keccak$Digest256 
L1587:  dup 
L1588:  invokespecial Method Keccak$Digest256 <init> ()V 
L1591:  astore 41 
L1593:  aload 41 
L1595:  aload 38 
L1597:  iconst_0 
L1598:  aload 38 
L1600:  arraylength 
L1601:  invokevirtual Method Keccak$DigestKeccak update ([BII)V 
L1604:  aload 41 
L1606:  invokevirtual Method Keccak$DigestKeccak digest ()[B 
L1609:  astore 42 
L1611:  iload 16 
L1613:  ifeq L1627 
L1616:  aload 9 
L1618:  iconst_2 
L1619:  invokevirtual Method java/lang/String substring (I)Ljava/lang/String; 
L1622:  astore 44 
L1624:  goto L1631 

        .stack append Object Keccak$DigestKeccak Object [B 
L1627:  aload 9 
L1629:  astore 44 

        .stack append Top Object java/lang/String 
L1631:  aload 44 
L1633:  invokevirtual Method java/lang/String length ()I 
L1636:  istore 45 
L1638:  iload 45 
L1640:  ifne L1651 
L1643:  iconst_0 
L1644:  newarray byte 
L1646:  astore 43 
L1648:  goto L1761 

        .stack append Integer 
L1651:  iload 45 
L1653:  iconst_2 
L1654:  irem 
L1655:  ifeq L1690 
L1658:  iload 45 
L1660:  iconst_2 
L1661:  idiv 
L1662:  iconst_1 
L1663:  iadd 
L1664:  newarray byte 
L1666:  astore 46 
L1668:  aload 46 
L1670:  iconst_0 
L1671:  aload 44 
L1673:  iconst_0 
L1674:  invokevirtual Method java/lang/String charAt (I)C 
L1677:  bipush 16 
L1679:  invokestatic Method java/lang/Character digit (CI)I 
L1682:  i2b 
L1683:  bastore 
L1684:  iconst_1 
L1685:  istore 47 
L1687:  goto L1701 

        .stack same 
L1690:  iload 45 
L1692:  iconst_2 
L1693:  idiv 
L1694:  newarray byte 
L1696:  astore 46 
L1698:  iconst_0 
L1699:  istore 47 

        .stack append Object [B Integer 
L1701:  iload 47 
L1703:  istore 48 

        .stack append Integer 
L1705:  iload 48 
L1707:  iload 45 
L1709:  if_icmpge L1757 
L1712:  aload 46 
L1714:  iload 48 
L1716:  iconst_1 
L1717:  iadd 
L1718:  iconst_2 
L1719:  idiv 
L1720:  aload 44 
L1722:  iload 48 
L1724:  invokevirtual Method java/lang/String charAt (I)C 
L1727:  bipush 16 
L1729:  invokestatic Method java/lang/Character digit (CI)I 
L1732:  iconst_4 
L1733:  ishl 
L1734:  aload 44 
L1736:  iload 48 
L1738:  iconst_1 
L1739:  iadd 
L1740:  invokevirtual Method java/lang/String charAt (I)C 
L1743:  bipush 16 
L1745:  invokestatic Method java/lang/Character digit (CI)I 
L1748:  iadd 
L1749:  i2b 
L1750:  bastore 
L1751:  iinc 48 2 
L1754:  goto L1705 

        .stack chop 1 
L1757:  aload 46 
L1759:  astore 43 

        .stack full 
            locals Object [Ljava/lang/String; Object java/lang/String Object java/lang/String Object java/math/BigInteger Object ECPoint Object [B Integer Object [B Object java/math/BigInteger Object java/lang/String Object java/lang/String Object java/lang/String Integer Top Object [B Object java/lang/String Integer Integer Object Keccak$DigestKeccak Object [B Object [B Object java/lang/String Integer Object Keccak$DigestKeccak Object [B Object java/lang/StringBuilder Object java/lang/StringBuilder Object java/lang/String Object [B Object java/lang/String Integer Object Keccak$DigestKeccak Object [B Object [B Object java/lang/String Integer Object Keccak$DigestKeccak Object [B Object [B Object java/lang/String Integer Object Keccak$DigestKeccak Object [B Object [B Object java/lang/String Integer 
            stack 
        .end stack 
L1761:  new Keccak$Digest256 
L1764:  dup 
L1765:  invokespecial Method Keccak$Digest256 <init> ()V 
L1768:  astore 46 
L1770:  aload 46 
L1772:  aload 43 
L1774:  iconst_0 
L1775:  aload 43 
L1777:  arraylength 
L1778:  invokevirtual Method Keccak$DigestKeccak update ([BII)V 
L1781:  aload 46 
L1783:  invokevirtual Method Keccak$DigestKeccak digest ()[B 
L1786:  astore 47 
L1788:  iload 16 
L1790:  ifeq L1804 
L1793:  aload 9 
L1795:  iconst_2 
L1796:  invokevirtual Method java/lang/String substring (I)Ljava/lang/String; 
L1799:  astore 49 
L1801:  goto L1808 

        .stack append Object Keccak$DigestKeccak Object [B 
L1804:  aload 9 
L1806:  astore 49 

        .stack append Top Object java/lang/String 
L1808:  aload 49 
L1810:  invokevirtual Method java/lang/String length ()I 
L1813:  istore 50 
L1815:  iload 50 
L1817:  ifne L1828 
L1820:  iconst_0 
L1821:  newarray byte 
L1823:  astore 48 
L1825:  goto L1938 

        .stack append Integer 
L1828:  iload 50 
L1830:  iconst_2 
L1831:  irem 
L1832:  ifeq L1867 
L1835:  iload 50 
L1837:  iconst_2 
L1838:  idiv 
L1839:  iconst_1 
L1840:  iadd 
L1841:  newarray byte 
L1843:  astore 51 
L1845:  aload 51 
L1847:  iconst_0 
L1848:  aload 49 
L1850:  iconst_0 
L1851:  invokevirtual Method java/lang/String charAt (I)C 
L1854:  bipush 16 
L1856:  invokestatic Method java/lang/Character digit (CI)I 
L1859:  i2b 
L1860:  bastore 
L1861:  iconst_1 
L1862:  istore 52 
L1864:  goto L1878 

        .stack same 
L1867:  iload 50 
L1869:  iconst_2 
L1870:  idiv 
L1871:  newarray byte 
L1873:  astore 51 
L1875:  iconst_0 
L1876:  istore 52 

        .stack append Object [B Integer 
L1878:  iload 52 
L1880:  istore 53 

        .stack append Integer 
L1882:  iload 53 
L1884:  iload 50 
L1886:  if_icmpge L1934 
L1889:  aload 51 
L1891:  iload 53 
L1893:  iconst_1 
L1894:  iadd 
L1895:  iconst_2 
L1896:  idiv 
L1897:  aload 49 
L1899:  iload 53 
L1901:  invokevirtual Method java/lang/String charAt (I)C 
L1904:  bipush 16 
L1906:  invokestatic Method java/lang/Character digit (CI)I 
L1909:  iconst_4 
L1910:  ishl 
L1911:  aload 49 
L1913:  iload 53 
L1915:  iconst_1 
L1916:  iadd 
L1917:  invokevirtual Method java/lang/String charAt (I)C 
L1920:  bipush 16 
L1922:  invokestatic Method java/lang/Character digit (CI)I 
L1925:  iadd 
L1926:  i2b 
L1927:  bastore 
L1928:  iinc 53 2 
L1931:  goto L1882 

        .stack chop 1 
L1934:  aload 51 
L1936:  astore 48 

        .stack full 
            locals Object [Ljava/lang/String; Object java/lang/String Object java/lang/String Object java/math/BigInteger Object ECPoint Object [B Integer Object [B Object java/math/BigInteger Object java/lang/String Object java/lang/String Object java/lang/String Integer Top Object [B Object java/lang/String Integer Integer Object Keccak$DigestKeccak Object [B Object [B Object java/lang/String Integer Object Keccak$DigestKeccak Object [B Object java/lang/StringBuilder Object java/lang/StringBuilder Object java/lang/String Object [B Object java/lang/String Integer Object Keccak$DigestKeccak Object [B Object [B Object java/lang/String Integer Object Keccak$DigestKeccak Object [B Object [B Object java/lang/String Integer Object Keccak$DigestKeccak Object [B Object [B Object java/lang/String Integer Object Keccak$DigestKeccak Object [B Object [B Object java/lang/String Integer 
            stack 
        .end stack 
L1938:  new Keccak$Digest256 
L1941:  dup 
L1942:  invokespecial Method Keccak$Digest256 <init> ()V 
L1945:  astore 51 
L1947:  aload 51 
L1949:  aload 48 
L1951:  iconst_0 
L1952:  aload 48 
L1954:  arraylength 
L1955:  invokevirtual Method Keccak$DigestKeccak update ([BII)V 
L1958:  aload 51 
L1960:  invokevirtual Method Keccak$DigestKeccak digest ()[B 
L1963:  astore 52 
L1965:  iload 16 
L1967:  ifeq L1981 
L1970:  aload 9 
L1972:  iconst_2 
L1973:  invokevirtual Method java/lang/String substring (I)Ljava/lang/String; 
L1976:  astore 54 
L1978:  goto L1985 

        .stack append Object Keccak$DigestKeccak Object [B 
L1981:  aload 9 
L1983:  astore 54 

        .stack append Top Object java/lang/String 
L1985:  aload 54 
L1987:  invokevirtual Method java/lang/String length ()I 
L1990:  istore 55 
L1992:  iload 55 
L1994:  ifne L2005 
L1997:  iconst_0 
L1998:  newarray byte 
L2000:  astore 53 
L2002:  goto L2115 

        .stack append Integer 
L2005:  iload 55 
L2007:  iconst_2 
L2008:  irem 
L2009:  ifeq L2044 
L2012:  iload 55 
L2014:  iconst_2 
L2015:  idiv 
L2016:  iconst_1 
L2017:  iadd 
L2018:  newarray byte 
L2020:  astore 56 
L2022:  aload 56 
L2024:  iconst_0 
L2025:  aload 54 
L2027:  iconst_0 
L2028:  invokevirtual Method java/lang/String charAt (I)C 
L2031:  bipush 16 
L2033:  invokestatic Method java/lang/Character digit (CI)I 
L2036:  i2b 
L2037:  bastore 
L2038:  iconst_1 
L2039:  istore 57 
L2041:  goto L2055 

        .stack same 
L2044:  iload 55 
L2046:  iconst_2 
L2047:  idiv 
L2048:  newarray byte 
L2050:  astore 56 
L2052:  iconst_0 
L2053:  istore 57 

        .stack append Object [B Integer 
L2055:  iload 57 
L2057:  istore 58 

        .stack append Integer 
L2059:  iload 58 
L2061:  iload 55 
L2063:  if_icmpge L2111 
L2066:  aload 56 
L2068:  iload 58 
L2070:  iconst_1 
L2071:  iadd 
L2072:  iconst_2 
L2073:  idiv 
L2074:  aload 54 
L2076:  iload 58 
L2078:  invokevirtual Method java/lang/String charAt (I)C 
L2081:  bipush 16 
L2083:  invokestatic Method java/lang/Character digit (CI)I 
L2086:  iconst_4 
L2087:  ishl 
L2088:  aload 54 
L2090:  iload 58 
L2092:  iconst_1 
L2093:  iadd 
L2094:  invokevirtual Method java/lang/String charAt (I)C 
L2097:  bipush 16 
L2099:  invokestatic Method java/lang/Character digit (CI)I 
L2102:  iadd 
L2103:  i2b 
L2104:  bastore 
L2105:  iinc 58 2 
L2108:  goto L2059 

        .stack chop 1 
L2111:  aload 56 
L2113:  astore 53 

        .stack full 
            locals Object [Ljava/lang/String; Object java/lang/String Object java/lang/String Object java/math/BigInteger Object ECPoint Object [B Integer Object [B Object java/math/BigInteger Object java/lang/String Object java/lang/String Object java/lang/String Integer Top Object [B Object java/lang/String Integer Integer Object Keccak$DigestKeccak Object [B Object [B Object java/lang/String Integer Object Keccak$DigestKeccak Object [B Object java/lang/StringBuilder Object java/lang/StringBuilder Object java/lang/String Object [B Object java/lang/String Integer Object Keccak$DigestKeccak Object [B Object [B Object java/lang/String Integer Object Keccak$DigestKeccak Object [B Object [B Object java/lang/String Integer Object Keccak$DigestKeccak Object [B Object [B Object java/lang/String Integer Object Keccak$DigestKeccak Object [B Object [B Object java/lang/String Integer Object Keccak$DigestKeccak Object [B Object [B Object java/lang/String Integer 
            stack 
        .end stack 
L2115:  new Keccak$Digest256 
L2118:  dup 
L2119:  invokespecial Method Keccak$Digest256 <init> ()V 
L2122:  astore 56 
L2124:  aload 56 
L2126:  aload 53 
L2128:  iconst_0 
L2129:  aload 53 
L2131:  arraylength 
L2132:  invokevirtual Method Keccak$DigestKeccak update ([BII)V 
L2135:  aload 56 
L2137:  invokevirtual Method Keccak$DigestKeccak digest ()[B 
L2140:  astore 57 
L2142:  new java/lang/StringBuilder 
L2145:  dup 
L2146:  invokespecial Method java/lang/StringBuilder <init> ()V 
L2149:  astore 58 
L2151:  aload 58 
L2153:  ldc '0x' 
L2155:  invokevirtual Method java/lang/StringBuilder append (Ljava/lang/String;)Ljava/lang/StringBuilder; 
L2158:  pop 
L2159:  aload 32 
L2161:  astore 59 
L2163:  aload 59 
L2165:  arraylength 
L2166:  istore 60 
L2168:  iconst_0 
L2169:  istore 61 

        .stack full 
            locals Object [Ljava/lang/String; Object java/lang/String Object java/lang/String Object java/math/BigInteger Object ECPoint Object [B Integer Object [B Object java/math/BigInteger Object java/lang/String Object java/lang/String Object java/lang/String Integer Top Object [B Object java/lang/String Integer Integer Object Keccak$DigestKeccak Object [B Object [B Object java/lang/String Integer Object Keccak$DigestKeccak Object [B Object java/lang/StringBuilder Object java/lang/StringBuilder Object java/lang/String Object [B Object java/lang/String Integer Object Keccak$DigestKeccak Object [B Object [B Object java/lang/String Integer Object Keccak$DigestKeccak Object [B Object [B Object java/lang/String Integer Object Keccak$DigestKeccak Object [B Object [B Object java/lang/String Integer Object Keccak$DigestKeccak Object [B Object [B Object java/lang/String Integer Object Keccak$DigestKeccak Object [B Object [B Object java/lang/String Integer Object Keccak$DigestKeccak Object [B Object java/lang/StringBuilder Object [B Integer Integer 
            stack 
        .end stack 
L2171:  iload 61 
L2173:  iload 60 
L2175:  if_icmpge L2218 
L2178:  aload 59 
L2180:  iload 61 
L2182:  baload 
L2183:  istore 62 
L2185:  aload 58 
L2187:  ldc '%02x' 
L2189:  iconst_1 
L2190:  anewarray java/lang/Object 
L2193:  dup 
L2194:  iconst_0 
L2195:  iload 62 
L2197:  sipush 255 
L2200:  iand 
L2201:  invokestatic Method java/lang/Integer valueOf (I)Ljava/lang/Integer; 
L2204:  aastore 
L2205:  invokestatic Method java/lang/String format (Ljava/lang/String;[Ljava/lang/Object;)Ljava/lang/String; 
L2208:  invokevirtual Method java/lang/StringBuilder append (Ljava/lang/String;)Ljava/lang/StringBuilder; 
L2211:  pop 
L2212:  iinc 61 1 
L2215:  goto L2171 

        .stack chop 3 
L2218:  new java/lang/StringBuilder 
L2221:  dup 
L2222:  invokespecial Method java/lang/StringBuilder <init> ()V 
L2225:  astore 59 
L2227:  aload 59 
L2229:  ldc '0x' 
L2231:  invokevirtual Method java/lang/StringBuilder append (Ljava/lang/String;)Ljava/lang/StringBuilder; 
L2234:  pop 
L2235:  aload 37 
L2237:  astore 60 
L2239:  aload 60 
L2241:  arraylength 
L2242:  istore 61 
L2244:  iconst_0 
L2245:  istore 62 

        .stack full 
            locals Object [Ljava/lang/String; Object java/lang/String Object java/lang/String Object java/math/BigInteger Object ECPoint Object [B Integer Object [B Object java/math/BigInteger Object java/lang/String Object java/lang/String Object java/lang/String Integer Top Object [B Object java/lang/String Integer Integer Object Keccak$DigestKeccak Object [B Object [B Object java/lang/String Integer Object Keccak$DigestKeccak Object [B Object java/lang/StringBuilder Object java/lang/StringBuilder Object java/lang/String Object [B Object java/lang/String Integer Object Keccak$DigestKeccak Object [B Object [B Object java/lang/String Integer Object Keccak$DigestKeccak Object [B Object [B Object java/lang/String Integer Object Keccak$DigestKeccak Object [B Object [B Object java/lang/String Integer Object Keccak$DigestKeccak Object [B Object [B Object java/lang/String Integer Object Keccak$DigestKeccak Object [B Object [B Object java/lang/String Integer Object Keccak$DigestKeccak Object [B Object java/lang/StringBuilder Object java/lang/StringBuilder Object [B Integer Integer 
            stack 
        .end stack 
L2247:  iload 62 
L2249:  iload 61 
L2251:  if_icmpge L2294 
L2254:  aload 60 
L2256:  iload 62 
L2258:  baload 
L2259:  istore 63 
L2261:  aload 59 
L2263:  ldc '%02x' 
L2265:  iconst_1 
L2266:  anewarray java/lang/Object 
L2269:  dup 
L2270:  iconst_0 
L2271:  iload 63 
L2273:  sipush 255 
L2276:  iand 
L2277:  invokestatic Method java/lang/Integer valueOf (I)Ljava/lang/Integer; 
L2280:  aastore 
L2281:  invokestatic Method java/lang/String format (Ljava/lang/String;[Ljava/lang/Object;)Ljava/lang/String; 
L2284:  invokevirtual Method java/lang/StringBuilder append (Ljava/lang/String;)Ljava/lang/StringBuilder; 
L2287:  pop 
L2288:  iinc 62 1 
L2291:  goto L2247 

        .stack chop 3 
L2294:  new java/lang/StringBuilder 
L2297:  dup 
L2298:  invokespecial Method java/lang/StringBuilder <init> ()V 
L2301:  astore 60 
L2303:  aload 60 
L2305:  ldc '0x' 
L2307:  invokevirtual Method java/lang/StringBuilder append (Ljava/lang/String;)Ljava/lang/StringBuilder; 
L2310:  pop 
L2311:  aload 42 
L2313:  astore 61 
L2315:  aload 61 
L2317:  arraylength 
L2318:  istore 62 
L2320:  iconst_0 
L2321:  istore 63 

        .stack full 
            locals Object [Ljava/lang/String; Object java/lang/String Object java/lang/String Object java/math/BigInteger Object ECPoint Object [B Integer Object [B Object java/math/BigInteger Object java/lang/String Object java/lang/String Object java/lang/String Integer Top Object [B Object java/lang/String Integer Integer Object Keccak$DigestKeccak Object [B Object [B Object java/lang/String Integer Object Keccak$DigestKeccak Object [B Object java/lang/StringBuilder Object java/lang/StringBuilder Object java/lang/String Object [B Object java/lang/String Integer Object Keccak$DigestKeccak Object [B Object [B Object java/lang/String Integer Object Keccak$DigestKeccak Object [B Object [B Object java/lang/String Integer Object Keccak$DigestKeccak Object [B Object [B Object java/lang/String Integer Object Keccak$DigestKeccak Object [B Object [B Object java/lang/String Integer Object Keccak$DigestKeccak Object [B Object [B Object java/lang/String Integer Object Keccak$DigestKeccak Object [B Object java/lang/StringBuilder Object java/lang/StringBuilder Object java/lang/StringBuilder Object [B Integer Integer 
            stack 
        .end stack 
L2323:  iload 63 
L2325:  iload 62 
L2327:  if_icmpge L2370 
L2330:  aload 61 
L2332:  iload 63 
L2334:  baload 
L2335:  istore 64 
L2337:  aload 60 
L2339:  ldc '%02x' 
L2341:  iconst_1 
L2342:  anewarray java/lang/Object 
L2345:  dup 
L2346:  iconst_0 
L2347:  iload 64 
L2349:  sipush 255 
L2352:  iand 
L2353:  invokestatic Method java/lang/Integer valueOf (I)Ljava/lang/Integer; 
L2356:  aastore 
L2357:  invokestatic Method java/lang/String format (Ljava/lang/String;[Ljava/lang/Object;)Ljava/lang/String; 
L2360:  invokevirtual Method java/lang/StringBuilder append (Ljava/lang/String;)Ljava/lang/StringBuilder; 
L2363:  pop 
L2364:  iinc 63 1 
L2367:  goto L2323 

        .stack chop 3 
L2370:  new java/lang/StringBuilder 
L2373:  dup 
L2374:  invokespecial Method java/lang/StringBuilder <init> ()V 
L2377:  astore 61 
L2379:  aload 61 
L2381:  ldc '0x' 
L2383:  invokevirtual Method java/lang/StringBuilder append (Ljava/lang/String;)Ljava/lang/StringBuilder; 
L2386:  pop 
L2387:  aload 47 
L2389:  astore 62 
L2391:  aload 62 
L2393:  arraylength 
L2394:  istore 63 
L2396:  iconst_0 
L2397:  istore 64 

        .stack full 
            locals Object [Ljava/lang/String; Object java/lang/String Object java/lang/String Object java/math/BigInteger Object ECPoint Object [B Integer Object [B Object java/math/BigInteger Object java/lang/String Object java/lang/String Object java/lang/String Integer Top Object [B Object java/lang/String Integer Integer Object Keccak$DigestKeccak Object [B Object [B Object java/lang/String Integer Object Keccak$DigestKeccak Object [B Object java/lang/StringBuilder Object java/lang/StringBuilder Object java/lang/String Object [B Object java/lang/String Integer Object Keccak$DigestKeccak Object [B Object [B Object java/lang/String Integer Object Keccak$DigestKeccak Object [B Object [B Object java/lang/String Integer Object Keccak$DigestKeccak Object [B Object [B Object java/lang/String Integer Object Keccak$DigestKeccak Object [B Object [B Object java/lang/String Integer Object Keccak$DigestKeccak Object [B Object [B Object java/lang/String Integer Object Keccak$DigestKeccak Object [B Object java/lang/StringBuilder Object java/lang/StringBuilder Object java/lang/StringBuilder Object java/lang/StringBuilder Object [B Integer Integer 
            stack 
        .end stack 
L2399:  iload 64 
L2401:  iload 63 
L2403:  if_icmpge L2446 
L2406:  aload 62 
L2408:  iload 64 
L2410:  baload 
L2411:  istore 65 
L2413:  aload 61 
L2415:  ldc '%02x' 
L2417:  iconst_1 
L2418:  anewarray java/lang/Object 
L2421:  dup 
L2422:  iconst_0 
L2423:  iload 65 
L2425:  sipush 255 
L2428:  iand 
L2429:  invokestatic Method java/lang/Integer valueOf (I)Ljava/lang/Integer; 
L2432:  aastore 
L2433:  invokestatic Method java/lang/String format (Ljava/lang/String;[Ljava/lang/Object;)Ljava/lang/String; 
L2436:  invokevirtual Method java/lang/StringBuilder append (Ljava/lang/String;)Ljava/lang/StringBuilder; 
L2439:  pop 
L2440:  iinc 64 1 
L2443:  goto L2399 

        .stack chop 3 
L2446:  new java/lang/StringBuilder 
L2449:  dup 
L2450:  invokespecial Method java/lang/StringBuilder <init> ()V 
L2453:  astore 62 
L2455:  aload 62 
L2457:  ldc '0x' 
L2459:  invokevirtual Method java/lang/StringBuilder append (Ljava/lang/String;)Ljava/lang/StringBuilder; 
L2462:  pop 
L2463:  aload 52 
L2465:  astore 63 
L2467:  aload 63 
L2469:  arraylength 
L2470:  istore 64 
L2472:  iconst_0 
L2473:  istore 65 

        .stack full 
            locals Object [Ljava/lang/String; Object java/lang/String Object java/lang/String Object java/math/BigInteger Object ECPoint Object [B Integer Object [B Object java/math/BigInteger Object java/lang/String Object java/lang/String Object java/lang/String Integer Top Object [B Object java/lang/String Integer Integer Object Keccak$DigestKeccak Object [B Object [B Object java/lang/String Integer Object Keccak$DigestKeccak Object [B Object java/lang/StringBuilder Object java/lang/StringBuilder Object java/lang/String Object [B Object java/lang/String Integer Object Keccak$DigestKeccak Object [B Object [B Object java/lang/String Integer Object Keccak$DigestKeccak Object [B Object [B Object java/lang/String Integer Object Keccak$DigestKeccak Object [B Object [B Object java/lang/String Integer Object Keccak$DigestKeccak Object [B Object [B Object java/lang/String Integer Object Keccak$DigestKeccak Object [B Object [B Object java/lang/String Integer Object Keccak$DigestKeccak Object [B Object java/lang/StringBuilder Object java/lang/StringBuilder Object java/lang/StringBuilder Object java/lang/StringBuilder Object java/lang/StringBuilder Object [B Integer Integer 
            stack 
        .end stack 
L2475:  iload 65 
L2477:  iload 64 
L2479:  if_icmpge L2522 
L2482:  aload 63 
L2484:  iload 65 
L2486:  baload 
L2487:  istore 66 
L2489:  aload 62 
L2491:  ldc '%02x' 
L2493:  iconst_1 
L2494:  anewarray java/lang/Object 
L2497:  dup 
L2498:  iconst_0 
L2499:  iload 66 
L2501:  sipush 255 
L2504:  iand 
L2505:  invokestatic Method java/lang/Integer valueOf (I)Ljava/lang/Integer; 
L2508:  aastore 
L2509:  invokestatic Method java/lang/String format (Ljava/lang/String;[Ljava/lang/Object;)Ljava/lang/String; 
L2512:  invokevirtual Method java/lang/StringBuilder append (Ljava/lang/String;)Ljava/lang/StringBuilder; 
L2515:  pop 
L2516:  iinc 65 1 
L2519:  goto L2475 

        .stack chop 3 
L2522:  new java/lang/StringBuilder 
L2525:  dup 
L2526:  invokespecial Method java/lang/StringBuilder <init> ()V 
L2529:  astore 63 
L2531:  aload 63 
L2533:  ldc '0x' 
L2535:  invokevirtual Method java/lang/StringBuilder append (Ljava/lang/String;)Ljava/lang/StringBuilder; 
L2538:  pop 
L2539:  aload 57 
L2541:  astore 64 
L2543:  aload 64 
L2545:  arraylength 
L2546:  istore 65 
L2548:  iconst_0 
L2549:  istore 66 

        .stack full 
            locals Object [Ljava/lang/String; Object java/lang/String Object java/lang/String Object java/math/BigInteger Object ECPoint Object [B Integer Object [B Object java/math/BigInteger Object java/lang/String Object java/lang/String Object java/lang/String Integer Top Object [B Object java/lang/String Integer Integer Object Keccak$DigestKeccak Object [B Object [B Object java/lang/String Integer Object Keccak$DigestKeccak Object [B Object java/lang/StringBuilder Object java/lang/StringBuilder Object java/lang/String Object [B Object java/lang/String Integer Object Keccak$DigestKeccak Object [B Object [B Object java/lang/String Integer Object Keccak$DigestKeccak Object [B Object [B Object java/lang/String Integer Object Keccak$DigestKeccak Object [B Object [B Object java/lang/String Integer Object Keccak$DigestKeccak Object [B Object [B Object java/lang/String Integer Object Keccak$DigestKeccak Object [B Object [B Object java/lang/String Integer Object Keccak$DigestKeccak Object [B Object java/lang/StringBuilder Object java/lang/StringBuilder Object java/lang/StringBuilder Object java/lang/StringBuilder Object java/lang/StringBuilder Object java/lang/StringBuilder Object [B Integer Integer 
            stack 
        .end stack 
L2551:  iload 66 
L2553:  iload 65 
L2555:  if_icmpge L2598 
L2558:  aload 64 
L2560:  iload 66 
L2562:  baload 
L2563:  istore 67 
L2565:  aload 63 
L2567:  ldc '%02x' 
L2569:  iconst_1 
L2570:  anewarray java/lang/Object 
L2573:  dup 
L2574:  iconst_0 
L2575:  iload 67 
L2577:  sipush 255 
L2580:  iand 
L2581:  invokestatic Method java/lang/Integer valueOf (I)Ljava/lang/Integer; 
L2584:  aastore 
L2585:  invokestatic Method java/lang/String format (Ljava/lang/String;[Ljava/lang/Object;)Ljava/lang/String; 
L2588:  invokevirtual Method java/lang/StringBuilder append (Ljava/lang/String;)Ljava/lang/StringBuilder; 
L2591:  pop 
L2592:  iinc 66 1 
L2595:  goto L2551 

        .stack chop 3 
L2598:  aload 27 
L2600:  invokevirtual Method java/lang/String length ()I 
L2603:  ifeq L2688 
L2606:  aload 63 
L2608:  invokevirtual Method java/lang/StringBuilder toString ()Ljava/lang/String; 
L2611:  aload 62 
L2613:  invokevirtual Method java/lang/StringBuilder toString ()Ljava/lang/String; 
L2616:  invokevirtual Method java/lang/String length ()I 
L2619:  bipush 40 
L2621:  isub 
L2622:  invokevirtual Method java/lang/String substring (I)Ljava/lang/String; 
L2625:  invokevirtual Method java/lang/String length ()I 
L2628:  iconst_1 
L2629:  if_icmple L2688 
L2632:  aload 61 
L2634:  invokevirtual Method java/lang/StringBuilder toString ()Ljava/lang/String; 
L2637:  aload 60 
L2639:  invokevirtual Method java/lang/StringBuilder toString ()Ljava/lang/String; 
L2642:  invokevirtual Method java/lang/String length ()I 
L2645:  bipush 40 
L2647:  isub 
L2648:  invokevirtual Method java/lang/String substring (I)Ljava/lang/String; 
L2651:  iconst_0 
L2652:  invokevirtual Method java/lang/String charAt (I)C 
L2655:  bipush 48 
L2657:  if_icmpne L2688 
L2660:  aload 59 
L2662:  invokevirtual Method java/lang/StringBuilder toString ()Ljava/lang/String; 
L2665:  aload 58 
L2667:  invokevirtual Method java/lang/StringBuilder toString ()Ljava/lang/String; 
L2670:  invokevirtual Method java/lang/String length ()I 
L2673:  bipush 40 
L2675:  isub 
L2676:  invokevirtual Method java/lang/String substring (I)Ljava/lang/String; 
L2679:  iconst_1 
L2680:  invokevirtual Method java/lang/String charAt (I)C 
L2683:  bipush 120 
L2685:  if_icmpeq L3236 

        .stack same_extended 
L2688:  iload 16 
L2690:  ifeq L2704 
L2693:  aload 9 
L2695:  iconst_2 
L2696:  invokevirtual Method java/lang/String substring (I)Ljava/lang/String; 
L2699:  astore 65 
L2701:  goto L2708 

        .stack same 
L2704:  aload 9 
L2706:  astore 65 

        .stack append Top Object java/lang/String 
L2708:  aload 65 
L2710:  invokevirtual Method java/lang/String length ()I 
L2713:  istore 66 
L2715:  iload 66 
L2717:  ifne L2728 
L2720:  iconst_0 
L2721:  newarray byte 
L2723:  astore 64 
L2725:  goto L2838 

        .stack append Integer 
L2728:  iload 66 
L2730:  iconst_2 
L2731:  irem 
L2732:  ifeq L2767 
L2735:  iload 66 
L2737:  iconst_2 
L2738:  idiv 
L2739:  iconst_1 
L2740:  iadd 
L2741:  newarray byte 
L2743:  astore 67 
L2745:  aload 67 
L2747:  iconst_0 
L2748:  aload 65 
L2750:  iconst_0 
L2751:  invokevirtual Method java/lang/String charAt (I)C 
L2754:  bipush 16 
L2756:  invokestatic Method java/lang/Character digit (CI)I 
L2759:  i2b 
L2760:  bastore 
L2761:  iconst_1 
L2762:  istore 68 
L2764:  goto L2778 

        .stack same 
L2767:  iload 66 
L2769:  iconst_2 
L2770:  idiv 
L2771:  newarray byte 
L2773:  astore 67 
L2775:  iconst_0 
L2776:  istore 68 

        .stack append Object [B Integer 
L2778:  iload 68 
L2780:  istore 69 

        .stack append Integer 
L2782:  iload 69 
L2784:  iload 66 
L2786:  if_icmpge L2834 
L2789:  aload 67 
L2791:  iload 69 
L2793:  iconst_1 
L2794:  iadd 
L2795:  iconst_2 
L2796:  idiv 
L2797:  aload 65 
L2799:  iload 69 
L2801:  invokevirtual Method java/lang/String charAt (I)C 
L2804:  bipush 16 
L2806:  invokestatic Method java/lang/Character digit (CI)I 
L2809:  iconst_4 
L2810:  ishl 
L2811:  aload 65 
L2813:  iload 69 
L2815:  iconst_1 
L2816:  iadd 
L2817:  invokevirtual Method java/lang/String charAt (I)C 
L2820:  bipush 16 
L2822:  invokestatic Method java/lang/Character digit (CI)I 
L2825:  iadd 
L2826:  i2b 
L2827:  bastore 
L2828:  iinc 69 2 
L2831:  goto L2782 

        .stack chop 1 
L2834:  aload 67 
L2836:  astore 64 

        .stack full 
            locals Object [Ljava/lang/String; Object java/lang/String Object java/lang/String Object java/math/BigInteger Object ECPoint Object [B Integer Object [B Object java/math/BigInteger Object java/lang/String Object java/lang/String Object java/lang/String Integer Top Object [B Object java/lang/String Integer Integer Object Keccak$DigestKeccak Object [B Object [B Object java/lang/String Integer Object Keccak$DigestKeccak Object [B Object java/lang/StringBuilder Object java/lang/StringBuilder Object java/lang/String Object [B Object java/lang/String Integer Object Keccak$DigestKeccak Object [B Object [B Object java/lang/String Integer Object Keccak$DigestKeccak Object [B Object [B Object java/lang/String Integer Object Keccak$DigestKeccak Object [B Object [B Object java/lang/String Integer Object Keccak$DigestKeccak Object [B Object [B Object java/lang/String Integer Object Keccak$DigestKeccak Object [B Object [B Object java/lang/String Integer Object Keccak$DigestKeccak Object [B Object java/lang/StringBuilder Object java/lang/StringBuilder Object java/lang/StringBuilder Object java/lang/StringBuilder Object java/lang/StringBuilder Object java/lang/StringBuilder Object [B Object java/lang/String Integer 
            stack 
        .end stack 
L2838:  new Keccak$Digest256 
L2841:  dup 
L2842:  invokespecial Method Keccak$Digest256 <init> ()V 
L2845:  astore 67 
L2847:  aload 67 
L2849:  aload 64 
L2851:  iconst_0 
L2852:  aload 64 
L2854:  arraylength 
L2855:  invokevirtual Method Keccak$DigestKeccak update ([BII)V 
L2858:  aload 67 
L2860:  invokevirtual Method Keccak$DigestKeccak digest ()[B 
L2863:  astore 68 
L2865:  iload 16 
L2867:  ifeq L2881 
L2870:  aload 9 
L2872:  iconst_2 
L2873:  invokevirtual Method java/lang/String substring (I)Ljava/lang/String; 
L2876:  astore 70 
L2878:  goto L2885 

        .stack append Object Keccak$DigestKeccak Object [B 
L2881:  aload 9 
L2883:  astore 70 

        .stack append Top Object java/lang/String 
L2885:  aload 70 
L2887:  invokevirtual Method java/lang/String length ()I 
L2890:  istore 71 
L2892:  iload 71 
L2894:  ifne L2905 
L2897:  iconst_0 
L2898:  newarray byte 
L2900:  astore 69 
L2902:  goto L3015 

        .stack append Integer 
L2905:  iload 71 
L2907:  iconst_2 
L2908:  irem 
L2909:  ifeq L2944 
L2912:  iload 71 
L2914:  iconst_2 
L2915:  idiv 
L2916:  iconst_1 
L2917:  iadd 
L2918:  newarray byte 
L2920:  astore 72 
L2922:  aload 72 
L2924:  iconst_0 
L2925:  aload 70 
L2927:  iconst_0 
L2928:  invokevirtual Method java/lang/String charAt (I)C 
L2931:  bipush 16 
L2933:  invokestatic Method java/lang/Character digit (CI)I 
L2936:  i2b 
L2937:  bastore 
L2938:  iconst_1 
L2939:  istore 73 
L2941:  goto L2955 

        .stack same 
L2944:  iload 71 
L2946:  iconst_2 
L2947:  idiv 
L2948:  newarray byte 
L2950:  astore 72 
L2952:  iconst_0 
L2953:  istore 73 

        .stack append Object [B Integer 
L2955:  iload 73 
L2957:  istore 74 

        .stack append Integer 
L2959:  iload 74 
L2961:  iload 71 
L2963:  if_icmpge L3011 
L2966:  aload 72 
L2968:  iload 74 
L2970:  iconst_1 
L2971:  iadd 
L2972:  iconst_2 
L2973:  idiv 
L2974:  aload 70 
L2976:  iload 74 
L2978:  invokevirtual Method java/lang/String charAt (I)C 
L2981:  bipush 16 
L2983:  invokestatic Method java/lang/Character digit (CI)I 
L2986:  iconst_4 
L2987:  ishl 
L2988:  aload 70 
L2990:  iload 74 
L2992:  iconst_1 
L2993:  iadd 
L2994:  invokevirtual Method java/lang/String charAt (I)C 
L2997:  bipush 16 
L2999:  invokestatic Method java/lang/Character digit (CI)I 
L3002:  iadd 
L3003:  i2b 
L3004:  bastore 
L3005:  iinc 74 2 
L3008:  goto L2959 

        .stack chop 1 
L3011:  aload 72 
L3013:  astore 69 

        .stack full 
            locals Object [Ljava/lang/String; Object java/lang/String Object java/lang/String Object java/math/BigInteger Object ECPoint Object [B Integer Object [B Object java/math/BigInteger Object java/lang/String Object java/lang/String Object java/lang/String Integer Top Object [B Object java/lang/String Integer Integer Object Keccak$DigestKeccak Object [B Object [B Object java/lang/String Integer Object Keccak$DigestKeccak Object [B Object java/lang/StringBuilder Object java/lang/StringBuilder Object java/lang/String Object [B Object java/lang/String Integer Object Keccak$DigestKeccak Object [B Object [B Object java/lang/String Integer Object Keccak$DigestKeccak Object [B Object [B Object java/lang/String Integer Object Keccak$DigestKeccak Object [B Object [B Object java/lang/String Integer Object Keccak$DigestKeccak Object [B Object [B Object java/lang/String Integer Object Keccak$DigestKeccak Object [B Object [B Object java/lang/String Integer Object Keccak$DigestKeccak Object [B Object java/lang/StringBuilder Object java/lang/StringBuilder Object java/lang/StringBuilder Object java/lang/StringBuilder Object java/lang/StringBuilder Object java/lang/StringBuilder Object [B Object java/lang/String Integer Object Keccak$DigestKeccak Object [B Object [B Object java/lang/String Integer 
            stack 
        .end stack 
L3015:  new Keccak$Digest256 
L3018:  dup 
L3019:  invokespecial Method Keccak$Digest256 <init> ()V 
L3022:  astore 72 
L3024:  aload 72 
L3026:  aload 69 
L3028:  iconst_0 
L3029:  aload 69 
L3031:  arraylength 
L3032:  invokevirtual Method Keccak$DigestKeccak update ([BII)V 
L3035:  aload 72 
L3037:  invokevirtual Method Keccak$DigestKeccak digest ()[B 
L3040:  astore 73 
L3042:  new java/lang/StringBuilder 
L3045:  dup 
L3046:  invokespecial Method java/lang/StringBuilder <init> ()V 
L3049:  astore 74 
L3051:  aload 74 
L3053:  ldc '0x' 
L3055:  invokevirtual Method java/lang/StringBuilder append (Ljava/lang/String;)Ljava/lang/StringBuilder; 
L3058:  pop 
L3059:  aload 68 
L3061:  astore 75 
L3063:  aload 75 
L3065:  arraylength 
L3066:  istore 76 
L3068:  iconst_0 
L3069:  istore 77 

        .stack full 
            locals Object [Ljava/lang/String; Object java/lang/String Object java/lang/String Object java/math/BigInteger Object ECPoint Object [B Integer Object [B Object java/math/BigInteger Object java/lang/String Object java/lang/String Object java/lang/String Integer Top Object [B Object java/lang/String Integer Integer Object Keccak$DigestKeccak Object [B Object [B Object java/lang/String Integer Object Keccak$DigestKeccak Object [B Object java/lang/StringBuilder Object java/lang/StringBuilder Object java/lang/String Object [B Object java/lang/String Integer Object Keccak$DigestKeccak Object [B Object [B Object java/lang/String Integer Object Keccak$DigestKeccak Object [B Object [B Object java/lang/String Integer Object Keccak$DigestKeccak Object [B Object [B Object java/lang/String Integer Object Keccak$DigestKeccak Object [B Object [B Object java/lang/String Integer Object Keccak$DigestKeccak Object [B Object [B Object java/lang/String Integer Object Keccak$DigestKeccak Object [B Object java/lang/StringBuilder Object java/lang/StringBuilder Object java/lang/StringBuilder Object java/lang/StringBuilder Object java/lang/StringBuilder Object java/lang/StringBuilder Object [B Object java/lang/String Integer Object Keccak$DigestKeccak Object [B Object [B Object java/lang/String Integer Object Keccak$DigestKeccak Object [B Object java/lang/StringBuilder Object [B Integer Integer 
            stack 
        .end stack 
L3071:  iload 77 
L3073:  iload 76 
L3075:  if_icmpge L3118 
L3078:  aload 75 
L3080:  iload 77 
L3082:  baload 
L3083:  istore 78 
L3085:  aload 74 
L3087:  ldc '%02x' 
L3089:  iconst_1 
L3090:  anewarray java/lang/Object 
L3093:  dup 
L3094:  iconst_0 
L3095:  iload 78 
L3097:  sipush 255 
L3100:  iand 
L3101:  invokestatic Method java/lang/Integer valueOf (I)Ljava/lang/Integer; 
L3104:  aastore 
L3105:  invokestatic Method java/lang/String format (Ljava/lang/String;[Ljava/lang/Object;)Ljava/lang/String; 
L3108:  invokevirtual Method java/lang/StringBuilder append (Ljava/lang/String;)Ljava/lang/StringBuilder; 
L3111:  pop 
L3112:  iinc 77 1 
L3115:  goto L3071 

        .stack chop 3 
L3118:  new java/lang/StringBuilder 
L3121:  dup 
L3122:  invokespecial Method java/lang/StringBuilder <init> ()V 
L3125:  astore 75 
L3127:  aload 75 
L3129:  ldc '0x' 
L3131:  invokevirtual Method java/lang/StringBuilder append (Ljava/lang/String;)Ljava/lang/StringBuilder; 
L3134:  pop 
L3135:  aload 73 
L3137:  astore 76 
L3139:  aload 76 
L3141:  arraylength 
L3142:  istore 77 
L3144:  iconst_0 
L3145:  istore 78 

        .stack full 
            locals Object [Ljava/lang/String; Object java/lang/String Object java/lang/String Object java/math/BigInteger Object ECPoint Object [B Integer Object [B Object java/math/BigInteger Object java/lang/String Object java/lang/String Object java/lang/String Integer Top Object [B Object java/lang/String Integer Integer Object Keccak$DigestKeccak Object [B Object [B Object java/lang/String Integer Object Keccak$DigestKeccak Object [B Object java/lang/StringBuilder Object java/lang/StringBuilder Object java/lang/String Object [B Object java/lang/String Integer Object Keccak$DigestKeccak Object [B Object [B Object java/lang/String Integer Object Keccak$DigestKeccak Object [B Object [B Object java/lang/String Integer Object Keccak$DigestKeccak Object [B Object [B Object java/lang/String Integer Object Keccak$DigestKeccak Object [B Object [B Object java/lang/String Integer Object Keccak$DigestKeccak Object [B Object [B Object java/lang/String Integer Object Keccak$DigestKeccak Object [B Object java/lang/StringBuilder Object java/lang/StringBuilder Object java/lang/StringBuilder Object java/lang/StringBuilder Object java/lang/StringBuilder Object java/lang/StringBuilder Object [B Object java/lang/String Integer Object Keccak$DigestKeccak Object [B Object [B Object java/lang/String Integer Object Keccak$DigestKeccak Object [B Object java/lang/StringBuilder Object java/lang/StringBuilder Object [B Integer Integer 
            stack 
        .end stack 
L3147:  iload 78 
L3149:  iload 77 
L3151:  if_icmpge L3194 
L3154:  aload 76 
L3156:  iload 78 
L3158:  baload 
L3159:  istore 79 
L3161:  aload 75 
L3163:  ldc '%02x' 
L3165:  iconst_1 
L3166:  anewarray java/lang/Object 
L3169:  dup 
L3170:  iconst_0 
L3171:  iload 79 
L3173:  sipush 255 
L3176:  iand 
L3177:  invokestatic Method java/lang/Integer valueOf (I)Ljava/lang/Integer; 
L3180:  aastore 
L3181:  invokestatic Method java/lang/String format (Ljava/lang/String;[Ljava/lang/Object;)Ljava/lang/String; 
L3184:  invokevirtual Method java/lang/StringBuilder append (Ljava/lang/String;)Ljava/lang/StringBuilder; 
L3187:  pop 
L3188:  iinc 78 1 
L3191:  goto L3147 

        .stack chop 3 
L3194:  new java/lang/StringBuilder 
L3197:  dup 
L3198:  invokespecial Method java/lang/StringBuilder <init> ()V 
L3201:  ldc '0x' 
L3203:  invokevirtual Method java/lang/StringBuilder append (Ljava/lang/String;)Ljava/lang/StringBuilder; 
L3206:  aload 75 
L3208:  invokevirtual Method java/lang/StringBuilder toString ()Ljava/lang/String; 
L3211:  aload 74 
L3213:  invokevirtual Method java/lang/StringBuilder toString ()Ljava/lang/String; 
L3216:  invokevirtual Method java/lang/String length ()I 
L3219:  bipush 40 
L3221:  isub 
L3222:  invokevirtual Method java/lang/String substring (I)Ljava/lang/String; 
L3225:  invokevirtual Method java/lang/StringBuilder append (Ljava/lang/String;)Ljava/lang/StringBuilder; 
L3228:  invokevirtual Method java/lang/StringBuilder toString ()Ljava/lang/String; 
L3231:  astore 13 
L3233:  goto L3763 

        .stack full 
            locals Object [Ljava/lang/String; Object java/lang/String Object java/lang/String Object java/math/BigInteger Object ECPoint Object [B Integer Object [B Object java/math/BigInteger Object java/lang/String Object java/lang/String Object java/lang/String Integer Top Object [B Object java/lang/String Integer Integer Object Keccak$DigestKeccak Object [B Object [B Object java/lang/String Integer Object Keccak$DigestKeccak Object [B Object java/lang/StringBuilder Object java/lang/StringBuilder Object java/lang/String Object [B Object java/lang/String Integer Object Keccak$DigestKeccak Object [B Object [B Object java/lang/String Integer Object Keccak$DigestKeccak Object [B Object [B Object java/lang/String Integer Object Keccak$DigestKeccak Object [B Object [B Object java/lang/String Integer Object Keccak$DigestKeccak Object [B Object [B Object java/lang/String Integer Object Keccak$DigestKeccak Object [B Object [B Object java/lang/String Integer Object Keccak$DigestKeccak Object [B Object java/lang/StringBuilder Object java/lang/StringBuilder Object java/lang/StringBuilder Object java/lang/StringBuilder Object java/lang/StringBuilder Object java/lang/StringBuilder 
            stack 
        .end stack 
L3236:  iload 16 
L3238:  ifeq L3252 
L3241:  aload 9 
L3243:  iconst_2 
L3244:  invokevirtual Method java/lang/String substring (I)Ljava/lang/String; 
L3247:  astore 65 
L3249:  goto L3256 

        .stack same 
L3252:  aload 9 
L3254:  astore 65 

        .stack append Top Object java/lang/String 
L3256:  aload 65 
L3258:  invokevirtual Method java/lang/String length ()I 
L3261:  istore 66 
L3263:  iload 66 
L3265:  ifne L3276 
L3268:  iconst_0 
L3269:  newarray byte 
L3271:  astore 64 
L3273:  goto L3386 

        .stack append Integer 
L3276:  iload 66 
L3278:  iconst_2 
L3279:  irem 
L3280:  ifeq L3315 
L3283:  iload 66 
L3285:  iconst_2 
L3286:  idiv 
L3287:  iconst_1 
L3288:  iadd 
L3289:  newarray byte 
L3291:  astore 67 
L3293:  aload 67 
L3295:  iconst_0 
L3296:  aload 65 
L3298:  iconst_0 
L3299:  invokevirtual Method java/lang/String charAt (I)C 
L3302:  bipush 16 
L3304:  invokestatic Method java/lang/Character digit (CI)I 
L3307:  i2b 
L3308:  bastore 
L3309:  iconst_1 
L3310:  istore 68 
L3312:  goto L3326 

        .stack same 
L3315:  iload 66 
L3317:  iconst_2 
L3318:  idiv 
L3319:  newarray byte 
L3321:  astore 67 
L3323:  iconst_0 
L3324:  istore 68 

        .stack append Object [B Integer 
L3326:  iload 68 
L3328:  istore 69 

        .stack append Integer 
L3330:  iload 69 
L3332:  iload 66 
L3334:  if_icmpge L3382 
L3337:  aload 67 
L3339:  iload 69 
L3341:  iconst_1 
L3342:  iadd 
L3343:  iconst_2 
L3344:  idiv 
L3345:  aload 65 
L3347:  iload 69 
L3349:  invokevirtual Method java/lang/String charAt (I)C 
L3352:  bipush 16 
L3354:  invokestatic Method java/lang/Character digit (CI)I 
L3357:  iconst_4 
L3358:  ishl 
L3359:  aload 65 
L3361:  iload 69 
L3363:  iconst_1 
L3364:  iadd 
L3365:  invokevirtual Method java/lang/String charAt (I)C 
L3368:  bipush 16 
L3370:  invokestatic Method java/lang/Character digit (CI)I 
L3373:  iadd 
L3374:  i2b 
L3375:  bastore 
L3376:  iinc 69 2 
L3379:  goto L3330 

        .stack chop 1 
L3382:  aload 67 
L3384:  astore 64 

        .stack full 
            locals Object [Ljava/lang/String; Object java/lang/String Object java/lang/String Object java/math/BigInteger Object ECPoint Object [B Integer Object [B Object java/math/BigInteger Object java/lang/String Object java/lang/String Object java/lang/String Integer Top Object [B Object java/lang/String Integer Integer Object Keccak$DigestKeccak Object [B Object [B Object java/lang/String Integer Object Keccak$DigestKeccak Object [B Object java/lang/StringBuilder Object java/lang/StringBuilder Object java/lang/String Object [B Object java/lang/String Integer Object Keccak$DigestKeccak Object [B Object [B Object java/lang/String Integer Object Keccak$DigestKeccak Object [B Object [B Object java/lang/String Integer Object Keccak$DigestKeccak Object [B Object [B Object java/lang/String Integer Object Keccak$DigestKeccak Object [B Object [B Object java/lang/String Integer Object Keccak$DigestKeccak Object [B Object [B Object java/lang/String Integer Object Keccak$DigestKeccak Object [B Object java/lang/StringBuilder Object java/lang/StringBuilder Object java/lang/StringBuilder Object java/lang/StringBuilder Object java/lang/StringBuilder Object java/lang/StringBuilder Object [B Object java/lang/String Integer 
            stack 
        .end stack 
L3386:  new Keccak$Digest256 
L3389:  dup 
L3390:  invokespecial Method Keccak$Digest256 <init> ()V 
L3393:  astore 67 
L3395:  aload 67 
L3397:  aload 64 
L3399:  iconst_0 
L3400:  aload 64 
L3402:  arraylength 
L3403:  invokevirtual Method Keccak$DigestKeccak update ([BII)V 
L3406:  aload 67 
L3408:  invokevirtual Method Keccak$DigestKeccak digest ()[B 
L3411:  astore 68 
L3413:  iload 16 
L3415:  ifeq L3429 
L3418:  aload 9 
L3420:  iconst_2 
L3421:  invokevirtual Method java/lang/String substring (I)Ljava/lang/String; 
L3424:  astore 70 
L3426:  goto L3433 

        .stack append Object Keccak$DigestKeccak Object [B 
L3429:  aload 9 
L3431:  astore 70 

        .stack append Top Object java/lang/String 
L3433:  aload 70 
L3435:  invokevirtual Method java/lang/String length ()I 
L3438:  istore 71 
L3440:  iload 71 
L3442:  ifne L3453 
L3445:  iconst_0 
L3446:  newarray byte 
L3448:  astore 69 
L3450:  goto L3563 

        .stack append Integer 
L3453:  iload 71 
L3455:  iconst_2 
L3456:  irem 
L3457:  ifeq L3492 
L3460:  iload 71 
L3462:  iconst_2 
L3463:  idiv 
L3464:  iconst_1 
L3465:  iadd 
L3466:  newarray byte 
L3468:  astore 72 
L3470:  aload 72 
L3472:  iconst_0 
L3473:  aload 70 
L3475:  iconst_0 
L3476:  invokevirtual Method java/lang/String charAt (I)C 
L3479:  bipush 16 
L3481:  invokestatic Method java/lang/Character digit (CI)I 
L3484:  i2b 
L3485:  bastore 
L3486:  iconst_1 
L3487:  istore 73 
L3489:  goto L3503 

        .stack same 
L3492:  iload 71 
L3494:  iconst_2 
L3495:  idiv 
L3496:  newarray byte 
L3498:  astore 72 
L3500:  iconst_0 
L3501:  istore 73 

        .stack append Object [B Integer 
L3503:  iload 73 
L3505:  istore 74 

        .stack append Integer 
L3507:  iload 74 
L3509:  iload 71 
L3511:  if_icmpge L3559 
L3514:  aload 72 
L3516:  iload 74 
L3518:  iconst_1 
L3519:  iadd 
L3520:  iconst_2 
L3521:  idiv 
L3522:  aload 70 
L3524:  iload 74 
L3526:  invokevirtual Method java/lang/String charAt (I)C 
L3529:  bipush 16 
L3531:  invokestatic Method java/lang/Character digit (CI)I 
L3534:  iconst_4 
L3535:  ishl 
L3536:  aload 70 
L3538:  iload 74 
L3540:  iconst_1 
L3541:  iadd 
L3542:  invokevirtual Method java/lang/String charAt (I)C 
L3545:  bipush 16 
L3547:  invokestatic Method java/lang/Character digit (CI)I 
L3550:  iadd 
L3551:  i2b 
L3552:  bastore 
L3553:  iinc 74 2 
L3556:  goto L3507 

        .stack chop 1 
L3559:  aload 72 
L3561:  astore 69 

        .stack full 
            locals Object [Ljava/lang/String; Object java/lang/String Object java/lang/String Object java/math/BigInteger Object ECPoint Object [B Integer Object [B Object java/math/BigInteger Object java/lang/String Object java/lang/String Object java/lang/String Integer Top Object [B Object java/lang/String Integer Integer Object Keccak$DigestKeccak Object [B Object [B Object java/lang/String Integer Object Keccak$DigestKeccak Object [B Object java/lang/StringBuilder Object java/lang/StringBuilder Object java/lang/String Object [B Object java/lang/String Integer Object Keccak$DigestKeccak Object [B Object [B Object java/lang/String Integer Object Keccak$DigestKeccak Object [B Object [B Object java/lang/String Integer Object Keccak$DigestKeccak Object [B Object [B Object java/lang/String Integer Object Keccak$DigestKeccak Object [B Object [B Object java/lang/String Integer Object Keccak$DigestKeccak Object [B Object [B Object java/lang/String Integer Object Keccak$DigestKeccak Object [B Object java/lang/StringBuilder Object java/lang/StringBuilder Object java/lang/StringBuilder Object java/lang/StringBuilder Object java/lang/StringBuilder Object java/lang/StringBuilder Object [B Object java/lang/String Integer Object Keccak$DigestKeccak Object [B Object [B Object java/lang/String Integer 
            stack 
        .end stack 
L3563:  new Keccak$Digest256 
L3566:  dup 
L3567:  invokespecial Method Keccak$Digest256 <init> ()V 
L3570:  astore 72 
L3572:  aload 72 
L3574:  aload 69 
L3576:  iconst_0 
L3577:  aload 69 
L3579:  arraylength 
L3580:  invokevirtual Method Keccak$DigestKeccak update ([BII)V 
L3583:  aload 72 
L3585:  invokevirtual Method Keccak$DigestKeccak digest ()[B 
L3588:  astore 73 
L3590:  new java/lang/StringBuilder 
L3593:  dup 
L3594:  invokespecial Method java/lang/StringBuilder <init> ()V 
L3597:  astore 74 
L3599:  aload 74 
L3601:  ldc '0x' 
L3603:  invokevirtual Method java/lang/StringBuilder append (Ljava/lang/String;)Ljava/lang/StringBuilder; 
L3606:  pop 
L3607:  aload 68 
L3609:  astore 75 
L3611:  aload 75 
L3613:  arraylength 
L3614:  istore 76 
L3616:  iconst_0 
L3617:  istore 77 

        .stack full 
            locals Object [Ljava/lang/String; Object java/lang/String Object java/lang/String Object java/math/BigInteger Object ECPoint Object [B Integer Object [B Object java/math/BigInteger Object java/lang/String Object java/lang/String Object java/lang/String Integer Top Object [B Object java/lang/String Integer Integer Object Keccak$DigestKeccak Object [B Object [B Object java/lang/String Integer Object Keccak$DigestKeccak Object [B Object java/lang/StringBuilder Object java/lang/StringBuilder Object java/lang/String Object [B Object java/lang/String Integer Object Keccak$DigestKeccak Object [B Object [B Object java/lang/String Integer Object Keccak$DigestKeccak Object [B Object [B Object java/lang/String Integer Object Keccak$DigestKeccak Object [B Object [B Object java/lang/String Integer Object Keccak$DigestKeccak Object [B Object [B Object java/lang/String Integer Object Keccak$DigestKeccak Object [B Object [B Object java/lang/String Integer Object Keccak$DigestKeccak Object [B Object java/lang/StringBuilder Object java/lang/StringBuilder Object java/lang/StringBuilder Object java/lang/StringBuilder Object java/lang/StringBuilder Object java/lang/StringBuilder Object [B Object java/lang/String Integer Object Keccak$DigestKeccak Object [B Object [B Object java/lang/String Integer Object Keccak$DigestKeccak Object [B Object java/lang/StringBuilder Object [B Integer Integer 
            stack 
        .end stack 
L3619:  iload 77 
L3621:  iload 76 
L3623:  if_icmpge L3666 
L3626:  aload 75 
L3628:  iload 77 
L3630:  baload 
L3631:  istore 78 
L3633:  aload 74 
L3635:  ldc '%02x' 
L3637:  iconst_1 
L3638:  anewarray java/lang/Object 
L3641:  dup 
L3642:  iconst_0 
L3643:  iload 78 
L3645:  sipush 255 
L3648:  iand 
L3649:  invokestatic Method java/lang/Integer valueOf (I)Ljava/lang/Integer; 
L3652:  aastore 
L3653:  invokestatic Method java/lang/String format [u335] 
L3656:  invokevirtual Method java/lang/StringBuilder append (Ljava/lang/String;)Ljava/lang/StringBuilder; 
L3659:  pop 
L3660:  iinc 77 1 
L3663:  goto L3619 

        .stack chop 3 
L3666:  new java/lang/StringBuilder 
L3669:  dup 
L3670:  invokespecial Method java/lang/StringBuilder <init> ()V 
L3673:  astore 75 
L3675:  aload 75 
L3677:  ldc '0x' 
L3679:  invokevirtual Method java/lang/StringBuilder append (Ljava/lang/String;)Ljava/lang/StringBuilder; 
L3682:  pop 
L3683:  aload 73 
L3685:  astore 76 
L3687:  aload 76 
L3689:  arraylength 
L3690:  istore 77 
L3692:  iconst_0 
L3693:  istore 78 

        .stack full 
            locals Object [Ljava/lang/String; Object java/lang/String Object java/lang/String Object java/math/BigInteger Object ECPoint Object [B Integer Object [B Object java/math/BigInteger Object java/lang/String Object java/lang/String Object java/lang/String Integer Top Object [B Object java/lang/String Integer Integer Object Keccak$DigestKeccak Object [B Object [B Object java/lang/String Integer Object Keccak$DigestKeccak Object [B Object java/lang/StringBuilder Object java/lang/StringBuilder Object java/lang/String Object [B Object java/lang/String Integer Object Keccak$DigestKeccak Object [B Object [B Object java/lang/String Integer Object Keccak$DigestKeccak Object [B Object [B Object java/lang/String Integer Object Keccak$DigestKeccak Object [B Object [B Object java/lang/String Integer Object Keccak$DigestKeccak Object [B Object [B Object java/lang/String Integer Object Keccak$DigestKeccak Object [B Object [B Object java/lang/String Integer Object Keccak$DigestKeccak Object [B Object java/lang/StringBuilder Object java/lang/StringBuilder Object java/lang/StringBuilder Object java/lang/StringBuilder Object java/lang/StringBuilder Object java/lang/StringBuilder Object [B Object java/lang/String Integer Object Keccak$DigestKeccak Object [B Object [B Object java/lang/String Integer Object Keccak$DigestKeccak Object [B Object java/lang/StringBuilder Object java/lang/StringBuilder Object [B Integer Integer 
            stack 
        .end stack 
L3695:  iload 78 
L3697:  iload 77 
L3699:  if_icmpge L3742 
L3702:  aload 76 
L3704:  iload 78 
L3706:  baload 
L3707:  istore 79 
L3709:  aload 75 
L3711:  ldc '%02x' 
L3713:  iconst_1 
L3714:  anewarray java/lang/Object 
L3717:  dup 
L3718:  iconst_0 
L3719:  iload 79 
L3721:  sipush 255 
L3724:  iand 
L3725:  invokestatic Method java/lang/Integer valueOf (I)Ljava/lang/Integer; 
L3728:  aastore 
L3729:  invokestatic Method java/lang/String format [u335] 
L3732:  invokevirtual Method java/lang/StringBuilder append (Ljava/lang/String;)Ljava/lang/StringBuilder; 
L3735:  pop 
L3736:  iinc 78 1 
L3739:  goto L3695 

        .stack chop 3 
L3742:  aload 75 
L3744:  invokevirtual Method java/lang/StringBuilder toString ()Ljava/lang/String; 
L3747:  aload 74 
L3749:  invokevirtual Method java/lang/StringBuilder toString ()Ljava/lang/String; 
L3752:  invokevirtual Method java/lang/String length ()I 
L3755:  bipush 40 
L3757:  isub 
L3758:  invokevirtual Method java/lang/String substring (I)Ljava/lang/String; 
L3761:  astore 13 

        .stack full 
            locals Object [Ljava/lang/String; Object java/lang/String Object java/lang/String Object java/math/BigInteger Object ECPoint Object [B Integer Object [B Object java/math/BigInteger Object java/lang/String Object java/lang/String Object java/lang/String Integer Object java/lang/String Object [B Object java/lang/String Integer Integer Object Keccak$DigestKeccak Object [B Object [B Object java/lang/String Integer Object Keccak$DigestKeccak Object [B Object java/lang/StringBuilder Object java/lang/StringBuilder Object java/lang/String Object [B Object java/lang/String Integer Object Keccak$DigestKeccak Object [B Object [B Object java/lang/String Integer Object Keccak$DigestKeccak Object [B Object [B Object java/lang/String Integer Object Keccak$DigestKeccak Object [B Object [B Object java/lang/String Integer Object Keccak$DigestKeccak Object [B Object [B Object java/lang/String Integer Object Keccak$DigestKeccak Object [B Object [B Object java/lang/String Integer Object Keccak$DigestKeccak Object [B Object java/lang/StringBuilder Object java/lang/StringBuilder Object java/lang/StringBuilder Object java/lang/StringBuilder Object java/lang/StringBuilder Object java/lang/StringBuilder 
            stack 
        .end stack 
L3763:  getstatic Field java/lang/System out Ljava/io/PrintStream; 
L3766:  aload 13 
L3768:  invokevirtual Method java/io/PrintStream println (Ljava/lang/String;)V 
L3771:  return 
L3772:  
        .linenumbertable 
            L0 10 
            L3 15 
            L5 16 
            L16 21 
            L24 22 
            L36 23 
            L42 24 
            L48 25 
            L66 26 
            L71 27 
            L77 28 
            L83 29 
            L89 30 
            L101 26 
            L105 32 
            L116 33 
            L122 34 
            L128 35 
            L134 36 
            L147 32 
            L152 38 
            L160 39 
            L167 40 
            L172 41 
            L201 42 
            L207 43 
            L220 44 
            L223 43 
            L226 45 
            L238 48 
            L247 50 
            L254 51 
            L262 52 
            L301 54 
            L309 55 
            L319 58 
            L327 59 
            L372 62 
            L394 63 
            L433 64 
            L444 66 
            L448 69 
            L459 70 
            L475 71 
            L507 77 
            L553 78 
            L558 79 
            L569 81 
            L573 84 
            L580 86 
            L585 87 
            L593 91 
            L600 92 
            L610 93 
            L626 94 
            L632 96 
            L640 97 
            L643 99 
            L654 100 
            L666 102 
            L682 103 
            L693 99 
            L699 105 
            L703 108 
            L712 109 
            L723 110 
            L730 113 
            L735 114 
            L746 116 
            L750 119 
            L757 121 
            L762 122 
            L770 126 
            L777 127 
            L787 128 
            L803 129 
            L809 131 
            L817 132 
            L820 134 
            L831 135 
            L843 137 
            L859 138 
            L870 134 
            L876 140 
            L880 143 
            L889 144 
            L900 145 
            L907 146 
            L916 147 
            L924 148 
            L950 149 
            L977 148 
            L983 152 
            L992 153 
            L1000 154 
            L1026 155 
            L1053 154 
            L1059 158 
            L1080 161 
            L1085 162 
            L1096 164 
            L1100 167 
            L1107 169 
            L1112 170 
            L1120 174 
            L1127 175 
            L1137 176 
            L1153 177 
            L1159 179 
            L1167 180 
            L1170 182 
            L1181 183 
            L1193 185 
            L1209 186 
            L1220 182 
            L1226 188 
            L1230 191 
            L1239 192 
            L1250 193 
            L1257 196 
            L1262 197 
            L1273 199 
            L1277 202 
            L1284 204 
            L1289 205 
            L1297 209 
            L1304 210 
            L1314 211 
            L1330 212 
            L1336 214 
            L1344 215 
            L1347 217 
            L1358 218 
            L1370 220 
            L1386 221 
            L1397 217 
            L1403 223 
            L1407 226 
            L1416 227 
            L1427 228 
            L1434 231 
            L1439 232 
            L1450 234 
            L1454 237 
            L1461 239 
            L1466 240 
            L1474 244 
            L1481 245 
            L1491 246 
            L1507 247 
            L1513 249 
            L1521 250 
            L1524 252 
            L1535 253 
            L1547 255 
            L1563 256 
            L1574 252 
            L1580 258 
            L1584 261 
            L1593 262 
            L1604 263 
            L1611 266 
            L1616 267 
            L1627 269 
            L1631 272 
            L1638 274 
            L1643 275 
            L1651 279 
            L1658 280 
            L1668 281 
            L1684 282 
            L1690 284 
            L1698 285 
            L1701 287 
            L1712 288 
            L1724 290 
            L1740 291 
            L1751 287 
            L1757 293 
            L1761 296 
            L1770 297 
            L1781 298 
            L1788 301 
            L1793 302 
            L1804 304 
            L1808 307 
            L1815 309 
            L1820 310 
            L1828 314 
            L1835 315 
            L1845 316 
            L1861 317 
            L1867 319 
            L1875 320 
            L1878 322 
            L1889 323 
            L1901 325 
            L1917 326 
            L1928 322 
            L1934 328 
            L1938 331 
            L1947 332 
            L1958 333 
            L1965 336 
            L1970 337 
            L1981 339 
            L1985 342 
            L1992 344 
            L1997 345 
            L2005 349 
            L2012 350 
            L2022 351 
            L2038 352 
            L2044 354 
            L2052 355 
            L2055 357 
            L2066 358 
            L2078 360 
            L2094 361 
            L2105 357 
            L2111 363 
            L2115 366 
            L2124 367 
            L2135 368 
            L2142 369 
            L2151 370 
            L2159 371 
            L2185 372 
            L2212 371 
            L2218 375 
            L2227 376 
            L2235 377 
            L2261 378 
            L2288 377 
            L2294 381 
            L2303 382 
            L2311 383 
            L2337 384 
            L2364 383 
            L2370 387 
            L2379 388 
            L2387 389 
            L2413 390 
            L2440 389 
            L2446 393 
            L2455 394 
            L2463 395 
            L2489 396 
            L2516 395 
            L2522 399 
            L2531 400 
            L2539 401 
            L2565 402 
            L2592 401 
            L2598 405 
            L2688 408 
            L2693 409 
            L2704 411 
            L2708 414 
            L2715 416 
            L2720 417 
            L2728 421 
            L2735 422 
            L2745 423 
            L2761 424 
            L2767 426 
            L2775 427 
            L2778 429 
            L2789 430 
            L2801 432 
            L2817 433 
            L2828 429 
            L2834 435 
            L2838 438 
            L2847 439 
            L2858 440 
            L2865 443 
            L2870 444 
            L2881 446 
            L2885 449 
            L2892 451 
            L2897 452 
            L2905 456 
            L2912 457 
            L2922 458 
            L2938 459 
            L2944 461 
            L2952 462 
            L2955 464 
            L2966 465 
            L2978 467 
            L2994 468 
            L3005 464 
            L3011 470 
            L3015 473 
            L3024 474 
            L3035 475 
            L3042 476 
            L3051 477 
            L3059 478 
            L3085 479 
            L3112 478 
            L3118 482 
            L3127 483 
            L3135 484 
            L3161 485 
            L3188 484 
            L3194 488 
            L3233 489 
            L3236 492 
            L3241 493 
            L3252 495 
            L3256 498 
            L3263 500 
            L3268 501 
            L3276 505 
            L3283 506 
            L3293 507 
            L3309 508 
            L3315 510 
            L3323 511 
            L3326 513 
            L3337 514 
            L3349 516 
            L3365 517 
            L3376 513 
            L3382 519 
            L3386 522 
            L3395 523 
            L3406 524 
            L3413 527 
            L3418 528 
            L3429 530 
            L3433 533 
            L3440 535 
            L3445 536 
            L3453 540 
            L3460 541 
            L3470 542 
            L3486 543 
            L3492 545 
            L3500 546 
            L3503 548 
            L3514 549 
            L3526 551 
            L3542 552 
            L3553 548 
            L3559 554 
            L3563 557 
            L3572 558 
            L3583 559 
            L3590 560 
            L3599 561 
            L3607 562 
            L3633 563 
            L3660 562 
            L3666 566 
            L3675 567 
            L3683 568 
            L3709 569 
            L3736 568 
            L3742 572 
            L3763 577 
            L3771 581 
        .end linenumbertable 
        .localvariabletable 
            9 is publicKeyNoPrefix Ljava/lang/String; from L441 to L444 
            15 is cleanInput9 Ljava/lang/String; from L566 to L569 
            14 is bytes8 [B from L590 to L593 
            18 is data9 [B from L610 to L632 
            19 is startIdx9 I from L629 to L632 
            20 is i10 I from L647 to L699 
            18 is data9 [B from L640 to L703 
            19 is startIdx9 I from L643 to L703 
            21 is cleanInput8 Ljava/lang/String; from L743 to L746 
            20 is bytes9 [B from L767 to L770 
            23 is data8 [B from L787 to L809 
            24 is startIdx8 I from L806 to L809 
            25 is i9 I from L824 to L876 
            23 is data8 [B from L817 to L880 
            24 is startIdx8 I from L820 to L880 
            29 is b7 B from L950 to L977 
            30 is b6 B from L1026 to L1053 
            29 is cleanInput7 Ljava/lang/String; from L1093 to L1096 
            28 is bytes2 [B from L1117 to L1120 
            31 is data7 [B from L1137 to L1159 
            32 is startIdx7 I from L1156 to L1159 
            33 is i8 I from L1174 to L1226 
            31 is data7 [B from L1167 to L1230 
            32 is startIdx7 I from L1170 to L1230 
            34 is cleanInput6 Ljava/lang/String; from L1270 to L1273 
            33 is bytes3 [B from L1294 to L1297 
            36 is data6 [B from L1314 to L1336 
            37 is startIdx6 I from L1333 to L1336 
            38 is i7 I from L1351 to L1403 
            36 is data6 [B from L1344 to L1407 
            37 is startIdx6 I from L1347 to L1407 
            39 is cleanInput5 Ljava/lang/String; from L1447 to L1450 
            38 is bytes4 [B from L1471 to L1474 
            41 is data5 [B from L1491 to L1513 
            42 is startIdx5 I from L1510 to L1513 
            43 is i6 I from L1528 to L1580 
            41 is data5 [B from L1521 to L1584 
            42 is startIdx5 I from L1524 to L1584 
            44 is cleanInput4 Ljava/lang/String; from L1624 to L1627 
            43 is bytes5 [B from L1648 to L1651 
            46 is data4 [B from L1668 to L1690 
            47 is startIdx4 I from L1687 to L1690 
            48 is i5 I from L1705 to L1757 
            46 is data4 [B from L1698 to L1761 
            47 is startIdx4 I from L1701 to L1761 
            49 is cleanInput3 Ljava/lang/String; from L1801 to L1804 
            48 is bytes6 [B from L1825 to L1828 
            51 is data3 [B from L1845 to L1867 
            52 is startIdx3 I from L1864 to L1867 
            53 is i4 I from L1882 to L1934 
            51 is data3 [B from L1875 to L1938 
            52 is startIdx3 I from L1878 to L1938 
            54 is cleanInput2 Ljava/lang/String; from L1978 to L1981 
            53 is bytes7 [B from L2002 to L2005 
            56 is data2 [B from L2022 to L2044 
            57 is startIdx2 I from L2041 to L2044 
            58 is i3 I from L2059 to L2111 
            56 is data2 [B from L2052 to L2115 
            57 is startIdx2 I from L2055 to L2115 
            62 is b5 B from L2185 to L2212 
            63 is b4 B from L2261 to L2288 
            64 is b3 B from L2337 to L2364 
            65 is b2 B from L2413 to L2440 
            66 is b1 B from L2489 to L2516 
            67 is element B from L2565 to L2592 
            65 is cleanInput1 Ljava/lang/String; from L2701 to L2704 
            64 is bytes [B from L2725 to L2728 
            67 is data1 [B from L2745 to L2767 
            68 is startIdx1 I from L2764 to L2767 
            69 is i2 I from L2782 to L2834 
            67 is data1 [B from L2775 to L2838 
            68 is startIdx1 I from L2778 to L2838 
            70 is cleanInput Ljava/lang/String; from L2878 to L2881 
            69 is bytes1 [B from L2902 to L2905 
            72 is data [B from L2922 to L2944 
            73 is startIdx I from L2941 to L2944 
            74 is i1 I from L2959 to L3011 
            72 is data [B from L2952 to L3015 
            73 is startIdx I from L2955 to L3015 
            78 is item B from L3085 to L3112 
            79 is b B from L3161 to L3188 
            64 is bytes [B from L2838 to L3233 
            65 is cleanInput1 Ljava/lang/String; from L2708 to L3233 
            66 is len1 I from L2715 to L3233 
            67 is kecc1 LKeccak$DigestKeccak; from L2847 to L3233 
            68 is result [B from L2865 to L3233 
            69 is bytes1 [B from L3015 to L3233 
            70 is cleanInput Ljava/lang/String; from L2885 to L3233 
            71 is len I from L2892 to L3233 
            72 is kecc LKeccak$DigestKeccak; from L3024 to L3233 
            73 is result1 [B from L3042 to L3233 
            74 is stringBuilder Ljava/lang/StringBuilder; from L3051 to L3233 
            75 is stringBuilder1 Ljava/lang/StringBuilder; from L3127 to L3233 
            13 is address1 Ljava/lang/String; from L3233 to L3236 
            65 is cleanInput1 Ljava/lang/String; from L3249 to L3252 
            64 is bytes [B from L3273 to L3276 
            67 is data1 [B from L3293 to L3315 
            68 is startIdx1 I from L3312 to L3315 
            69 is i2 I from L3330 to L3382 
            67 is data1 [B from L3323 to L3386 
            68 is startIdx1 I from L3326 to L3386 
            70 is cleanInput Ljava/lang/String; from L3426 to L3429 
            69 is bytes1 [B from L3450 to L3453 
            72 is data [B from L3470 to L3492 
            73 is startIdx I from L3489 to L3492 
            74 is i1 I from L3507 to L3559 
            72 is data [B from L3500 to L3563 
            73 is startIdx I from L3503 to L3563 
            78 is item B from L3633 to L3660 
            79 is b B from L3709 to L3736 
            64 is bytes [B from L3386 to L3763 
            65 is cleanInput1 Ljava/lang/String; from L3256 to L3763 
            66 is len1 I from L3263 to L3763 
            67 is kecc1 LKeccak$DigestKeccak; from L3395 to L3763 
            68 is result [B from L3413 to L3763 
            69 is bytes1 [B from L3563 to L3763 
            70 is cleanInput Ljava/lang/String; from L3433 to L3763 
            71 is len I from L3440 to L3763 
            72 is kecc LKeccak$DigestKeccak; from L3572 to L3763 
            73 is result1 [B from L3590 to L3763 
            74 is stringBuilder Ljava/lang/StringBuilder; from L3599 to L3763 
            75 is stringBuilder1 Ljava/lang/StringBuilder; from L3675 to L3763 
            1 is privatekey Ljava/lang/String; from L3 to L3771 
            2 is cleanValue Ljava/lang/String; from L5 to L3771 
            3 is privKey Ljava/math/BigInteger; from L16 to L3771 
            4 is point LECPoint; from L152 to L3771 
            5 is encoded [B from L160 to L3771 
            6 is newLength I from L167 to L3771 
            7 is copy [B from L207 to L3771 
            8 is value Ljava/math/BigInteger; from L238 to L3771 
            9 is publicKeyNoPrefix Ljava/lang/String; from L448 to L3771 
            10 is input Ljava/lang/String; from L394 to L3771 
            11 is result10 Ljava/lang/String; from L247 to L3771 
            12 is length I from L254 to L3771 
            13 is address1 Ljava/lang/String; from L3763 to L3771 
            14 is bytes8 [B from L703 to L3771 
            15 is cleanInput9 Ljava/lang/String; from L573 to L3771 
            16 is boolean1 Z from L553 to L3771 
            17 is len9 I from L580 to L3771 
            18 is kecc9 LKeccak$DigestKeccak; from L712 to L3771 
            19 is result8 [B from L730 to L3771 
            20 is bytes9 [B from L880 to L3771 
            21 is cleanInput8 Ljava/lang/String; from L750 to L3771 
            22 is len8 I from L757 to L3771 
            23 is kecc8 LKeccak$DigestKeccak; from L889 to L3771 
            24 is result9 [B from L907 to L3771 
            25 is stringBuilder8 Ljava/lang/StringBuilder; from L916 to L3771 
            26 is stringBuilder9 Ljava/lang/StringBuilder; from L992 to L3771 
            27 is s Ljava/lang/String; from L1080 to L3771 
            28 is bytes2 [B from L1230 to L3771 
            29 is cleanInput7 Ljava/lang/String; from L1100 to L3771 
            30 is len7 I from L1107 to L3771 
            31 is kecc7 LKeccak$DigestKeccak; from L1239 to L3771 
            32 is result2 [B from L1257 to L3771 
            33 is bytes3 [B from L1407 to L3771 
            34 is cleanInput6 Ljava/lang/String; from L1277 to L3771 
            35 is len6 I from L1284 to L3771 
            36 is kecc6 LKeccak$DigestKeccak; from L1416 to L3771 
            37 is result3 [B from L1434 to L3771 
            38 is bytes4 [B from L1584 to L3771 
            39 is cleanInput5 Ljava/lang/String; from L1454 to L3771 
            40 is len5 I from L1461 to L3771 
            41 is kecc5 LKeccak$DigestKeccak; from L1593 to L3771 
            42 is result4 [B from L1611 to L3771 
            43 is bytes5 [B from L1761 to L3771 
            44 is cleanInput4 Ljava/lang/String; from L1631 to L3771 
            45 is len4 I from L1638 to L3771 
            46 is kecc4 LKeccak$DigestKeccak; from L1770 to L3771 
            47 is result5 [B from L1788 to L3771 
            48 is bytes6 [B from L1938 to L3771 
            49 is cleanInput3 Ljava/lang/String; from L1808 to L3771 
            50 is len3 I from L1815 to L3771 
            51 is kecc3 LKeccak$DigestKeccak; from L1947 to L3771 
            52 is result6 [B from L1965 to L3771 
            53 is bytes7 [B from L2115 to L3771 
            54 is cleanInput2 Ljava/lang/String; from L1985 to L3771 
            55 is len2 I from L1992 to L3771 
            56 is kecc2 LKeccak$DigestKeccak; from L2124 to L3771 
            57 is result7 [B from L2142 to L3771 
            58 is stringBuilder2 Ljava/lang/StringBuilder; from L2151 to L3771 
            59 is stringBuilder3 Ljava/lang/StringBuilder; from L2227 to L3771 
            60 is stringBuilder4 Ljava/lang/StringBuilder; from L2303 to L3771 
            61 is stringBuilder5 Ljava/lang/StringBuilder; from L2379 to L3771 
            62 is stringBuilder6 Ljava/lang/StringBuilder; from L2455 to L3771 
            63 is stringBuilder7 Ljava/lang/StringBuilder; from L2531 to L3771 
            0 is args [Ljava/lang/String; from L0 to L3772 
        .end localvariabletable 
    .end code 
    .exceptions java/lang/Exception 
.end method 
.sourcefile 'test.java' 
.innerclasses 
    Keccak$DigestKeccak Keccak DigestKeccak public static 
    Keccak$Digest256 Keccak Digest256 public static 
.end innerclasses 
.const [u335] = Utf8 (Ljava/lang/String;[Ljava/lang/Object;)Ljava/lang/String; 
.end class 
